[
  {
    "No": "0",
    "me": "Uhihihi! Ojou-sama~... You're hiding something in\nyour diaper, aren't you~ Gihiihiihii!"
  },
  {
    "No": "1",
    "me": "O-Ojou-sama~!... You've got poop on your butt~!\nGihiihiihii!"
  },
  {
    "No": "2",
    "me": "Uhihihi! A skirt dirtied with poop... It's\nembarrassing, isn't it!? Ihihii~!"
  },
  {
    "No": "3",
    "me": "Uhihihi! Your panties, they're stained with\npoop~... And they're Ojou-sama's panties too~"
  },
  {
    "No": "4",
    "me": "Uhihihi! Ojou-sama~... It looks like you should\nchange that diaper~! Gihiihiihii!"
  },
  {
    "No": "5",
    "me": "O-Ojou-sama~!... There are signs of something\nleaking from your crotch~! Gihiihiihii!"
  },
  {
    "No": "6",
    "me": "Uhihihi! A skirt stained with pee... It's\nembarrassing, isn't it!? Ihihii~!"
  },
  {
    "No": "7",
    "me": "Uhihihi! Your panties are soaked with pee~... And\nthey're Ojou-sama's too~"
  },
  {
    "No": "8",
    "me": "Muhehehe~ What does the body of a snobby Ojou-sama\nfeel like, huh?"
  },
  {
    "No": "9",
    "me": "Muhehehe~ Ojou-sama with the big butt, your pussy\nwas pretty decent~ Next time, I'll visually\nviolate that body of yours~"
  },
  {
    "No": "10",
    "me": "Muhehehe~ Ojou-sama's blowjob was pretty decent~\nNext time, I'll visually violate that body of\nyours~"
  },
  {
    "No": "11",
    "me": "Muhehehe~ Ojou-sama's ass hole! It was the best~\nNext time, I'll visually violate that body of\nyours~"
  },
  {
    "No": "12",
    "me": "Muhehehe~ Ojou-sama~ Did you know you've become\nmasturbation material? Gihiihiihii! Next time,\nI'll visually violate that body of yours~"
  },
  { "No": "13", "me": "Kuhaa~... Ahh~ I can smell Ojou-sama~" },
  {
    "No": "14",
    "me": "Haa haa haa... O-Ojou-sama~ Please return my\nshirt! Guhihiihii!"
  },
  {
    "No": "15",
    "me": "Haa haa haa... O-Ojou-sama~ Please return my\napron! Guhihiihii!"
  },
  {
    "No": "16",
    "me": "Haa haa haa... O-Ojou-sama~ Please return my\nswimsuit collection! Guhihiihii!"
  },
  {
    "No": "17",
    "me": "Haa haa haa... O-Ojou-sama~ Cardboard boxes don't\nsuit you~ Let's take it off, shall we~!\nGuhihiihii!"
  },
  {
    "No": "18",
    "me": "Haa haa haa... O-Ojou-sama~ Such a poor look\ndoesn't suit you~ Let's take it off, shall we~!\nGuhihiihii!"
  },
  { "No": "19", "me": "Uhehe! What's under Ojou-sama's skirt~? Gulp!" },
  {
    "No": "20",
    "me": "Haa haa haa... Ojou-sama, a high school girl's\nfresh shirt!... It's, it's exciting~"
  },
  {
    "No": "21",
    "me": "High school girl's loafers~! Gulp! Ahh~ Just this\nis enough for masturbation!"
  },
  {
    "No": "22",
    "me": "Ojou-sama, a high school girl's socks must have a\nnoble scent, right? Cough cough!... Guhehehehe!"
  },
  {
    "No": "23",
    "me": "Nhooh~ Nice, nice texture~ As expected, Ojou-\nsama's bra is different~ Uhehehehe!"
  },
  {
    "No": "24",
    "me": "Haa haa haa! High school girl's fresh panties!\nThe, the smell is so good!! Pre-cum release in 0.5\nseconds..."
  },
  {
    "No": "25",
    "me": "Haa haa haa! High school girl's fresh panties! And\nwith pee on them!! The, the smell is so good!!\nPre-cum release in 0.5 seconds..."
  },
  {
    "No": "26",
    "me": "Haa haa haa! High school girl's fresh panties! And\nwith pee & poop on them!! The, the complex smell\nis so good!! Cough cough!..."
  },
  {
    "No": "27",
    "me": "Haa haa haa! High school girl's worn diaper! The,\nthe smell is so good! This is an inevitable\nerection!"
  },
  {
    "No": "28",
    "me": "Haa haa haa! High school girl's worn diaper! And\nit's already been leaked in! This is an inevitable\nerection!"
  },
  {
    "No": "29",
    "me": "Haa haa haa! High school girl's worn diaper! And\nit's already been leaked and pooped in! This is\ntoo precious!"
  },
  {
    "No": "30",
    "me": "Haa haa haa! Ojou-sama~ Please return my briefs~\nGuhihiihii!"
  },
  {
    "No": "31",
    "me": "Haa haa haa! Ojou-sama~ Please return my towel~\nGuhihiihii!"
  },
  { "No": "32", "me": "Ojou-sama~ Please turn around~" },
  { "No": "33", "me": "Ojou-sama~ Please face forward~" },
  {
    "No": "34",
    "me": "Ha!? Eh, no, it's a misunderstanding! I was just\nthinking~ Ahahaha. (Damn! Such a cheeky brat!)"
  },
  {
    "No": "35",
    "me": "Ojou-sama's pussy~! The scent of bodily fluids\nseems to be wafting over~!"
  },
  { "No": "36", "me": "Uhee~! The scent of poop from the panties...\nCough!" },
  { "No": "37", "me": "Uhihihi! The skirt is turning brown~!" },
  { "No": "38", "me": "It stinks~! Ojou-sama's crotch stinks~! Buhahaha!" },
  { "No": "39", "me": "" },
  {
    "No": "40",
    "me": "Hey, old man! What are you looking at with such a\nlewd gaze!? It's super creepy!"
  },
  {
    "No": "41",
    "me": "Haa haa haa! High school girl's fresh panties! And\nwith filth on them!! It stinks!!..."
  },
  { "No": "42", "me": "" },
  { "No": "43", "me": "" },
  { "No": "44", "me": "" },
  { "No": "45", "me": "I'm really scared when I'm alone..." },
  {
    "No": "46",
    "me": "Now now, calm down~... I'm not thinking of eating\nyou or anything... (Guhyahya! I am thinking about\nit! Rape, rape!)"
  },
  {
    "No": "47",
    "me": "May I ask you something straight? Could you tell\nme... your weaknesses?"
  },
  {
    "No": "48",
    "me": "Ha!? Haa!? What are you saying!? (As if I'd tell\nyou that!!)"
  },
  {
    "No": "49",
    "me": "I thought school life was just boring, but then\nsuch a fun day comes around! It's super exciting!"
  },
  {
    "No": "50",
    "me": "No, if you're looking forward to it that much,\nI'll do my utmost to scare you~"
  },
  {
    "No": "51",
    "me": "Ah, is that so... (Even if you try that hard, it's\nstill kind of creepy...)"
  },
  {
    "No": "52",
    "me": "By the way, about the others who gathered tonight,\nI was wondering if you knew what scares them...\nany weaknesses you might be aware of. Do you know\nanything?"
  },
  { "No": "53", "me": "Ahh~! The janitor is trying to cheat~!" },
  {
    "No": "54",
    "me": "Hey, that's a bad way to put it~ It's not\ncheating, it's not..."
  },
  {
    "No": "55",
    "me": "If it's about Marimi Sasaki, I'd tell you! But the\nthing is I don't know anything about her~ Damn!\nIt's frustrating!"
  },
  { "No": "56", "me": "And she's not even here for the test of\ncourage!..." },
  {
    "No": "57",
    "me": "You mean Sasaki from the same class, right? I've\nheard that you've been bullying her... (Hehehe...)"
  },
  {
    "No": "58",
    "me": "Hmph! That's right! I hate her! The only things I\nbeat her in are my face and height! I lose to her\nin grades... even though I'm older!"
  },
  {
    "No": "59",
    "me": "Oh? Ah, you're a second-year, right? Is jealousy\nthe main reason for the bullying? Kukuku"
  },
  {
    "No": "60",
    "me": "Ah! There's another thing you're better at, you\nknow~ Your butt! Your butt size is definitely\nbigger~!"
  },
  {
    "No": "61",
    "me": "Shut up!! It's the opposite with hips! I hate that\nthey're too big! Small breasts but a big ass! Grr!\nYou perverted janitor! You're lewd!!..."
  },
  {
    "No": "62",
    "me": "Oops! Don't get me wrong~... I'm saying it's very\nattractive..."
  },
  { "No": "63", "me": "Attractive!?... Hmph!..." },
  {
    "No": "64",
    "me": "So, you don't know the weaknesses of the other\ngirls..."
  },
  {
    "No": "65",
    "me": "Tsukasa is quite a scaredy-cat... She's a bit shy\naround people."
  },
  {
    "No": "66",
    "me": "Hmm? You're talking about Tsukasa Hayashi, right?\nInterpersonal stuff might be effective..."
  },
  { "No": "67", "me": "I don't know about anyone else here." },
  { "No": "68", "me": "" },
  {
    "No": "69",
    "me": "I was a bit scared before doing it, but this is\nbad...! It's kind of hilarious! I'm gonna brag\nabout this to everyone tomorrow!"
  },
  {
    "No": "70",
    "me": "I was a bit scared before doing it, but now this\nis the best~! Seriously hilarious! I can see this\nbecoming a rumor!"
  },
  {
    "No": "71",
    "me": "Oh~ Thank you very much, if you say that much, it\nmakes me feel like my efforts were worth it...\n(Grr, it's frustrating!! I missed my chance to\nfuck this insolent girl!)"
  },
  { "No": "72", "me": "" },
  { "No": "73", "me": "" },
  {
    "No": "74",
    "me": "Hey janitor! What is this!? I'm super pissed off!\nHah!? Hah~!?"
  },
  {
    "No": "75",
    "me": "Hauh, ugh... S-s-sorry... (Why am I apologizing!?\nThis damn brat!!) (I want to hit her and shove my\ndick in!! Damn it!!)"
  },
  { "No": "76", "me": "Ah, so annoying~" },
  { "No": "77", "me": "Ha, ha!?~... (So frustrating~!)" },
  { "No": "78", "me": "" },
  {
    "No": "79",
    "me": "Hey, isn't that too much!? Knocking out a high\nschool girl like that!"
  },
  {
    "No": "80",
    "me": "Aha~ My apologies, it seems the stimulation was a\nbit too strong... (Bwahaha! Serves you right!)"
  },
  {
    "No": "81",
    "me": "If you tell anyone I fainted, I won't forgive you!\nI'll crush you with all my might!!"
  },
  {
    "No": "82",
    "me": "Oh ho, please don't threaten me like that~ My\nheart's already pounding... (I want to spread the\nword~ Hehehe!)"
  },
  { "No": "83", "me": "I don't know anything!!" },
  { "No": "84", "me": "" },
  {
    "No": "85",
    "me": "Hey, isn't that too harsh!? You're scaring a frail\nhigh school girl too much!! That's way over the\nline! Ahh~ I'm so mad!!"
  },
  {
    "No": "86",
    "me": "(The worst, seriously the worst. Ahh! I can't\nbelieve it!!) (Me, of all people, to wet myself!!)\n(It's a good thing I was wearing a diaper...)"
  },
  {
    "No": "87",
    "me": "Aha~ My apologies, it seems the stimulation was a\nbit too strong... (Bwahaha! Serves you right!)"
  },
  {
    "No": "88",
    "me": "Aha~ My apologies, it seems the stimulation was a\nbit too strong... (Bwahaha! Serves you right!\nKuh~!) (The smell of her shit is intense!)"
  },
  {
    "No": "89",
    "me": "If you tell anyone about this, I won't forgive\nyou! I'll crush you with all my might!!"
  },
  { "No": "90", "me": "Like I care about that!..." },
  { "No": "91", "me": "" },
  {
    "No": "92",
    "me": "Augh, ugh~!! This is the worst... Ahh! (Me... to\npee myself!!...) (This is a nightmare, a\nnightmare!)"
  },
  {
    "No": "93",
    "me": "Aha~ My apologies, it seems the stimulation was a\nbit too strong... Hehe, I didn't expect someone to\nwet themselves... Pfft..."
  },
  {
    "No": "94",
    "me": "Shut up!! I just wasn't feeling well, that's\nall... it's not like that! I'm saying I spilled\nwater, got it!? Tch, Tch!!"
  },
  {
    "No": "95",
    "me": "Augh, ugh~!! This is the worst... Ahh! (Me... to\nshit myself!!...) (This is a nightmare, a\nnightmare!)"
  },
  {
    "No": "96",
    "me": "Aha~ My apologies, it seems the stimulation was a\nbit too strong... Hehe, I didn't expect someone to\ndefecate... Pfft..."
  },
  {
    "No": "97",
    "me": "Shut up!! I just wasn't feeling well, that's\nall... it's not like that! I'm saying I sat on dog\npoop, got it!? Tch, Tch!!"
  },
  { "No": "98", "me": "Ah, yes, yes. That's what happened..." },
  { "No": "99", "me": "" },
  {
    "No": "100",
    "me": "Hey, isn't that a bit too much!? Making a high\nschool girl faint! That's going way too far! Ahh~\nI'm so pissed off!!"
  },
  {
    "No": "101",
    "me": "Aha~ My apologies, it seems the stimulation was a\nbit too strong... Hehe, I didn't expect someone to\ndefecate... Pfft... Your upper body is all\ndrenched too."
  },
  {
    "No": "102",
    "me": "Aha~ My apologies, it seems the stimulation was a\nbit too strong... Hehe, I didn't expect someone to\nwet themselves... Pfft... Your upper body is all\ndrenched too."
  },
  { "No": "103", "me": "" },
  { "No": "104", "me": "Ugh, ah, what!? Is my stomach upset?..." },
  { "No": "105", "me": "Ow, it hurts..." },
  { "No": "106", "me": "" },
  {
    "No": "107",
    "me": "Hey, wait a minute! I guess this is good...\nChanging into my own clothes..."
  },
  {
    "No": "108",
    "me": "Huh? Is that so? It smells pretty bad though...\nAre you sure? (Hehehe! Hehehe!)"
  },
  { "No": "109", "me": "" },
  {
    "No": "110",
    "me": "Nnah, ahh! Ugh... (Crap! Crap! This sensation,\nit's poop, isn't it!?) (This is bad! My crotch is\ngoing to be covered in poop!)"
  },
  {
    "No": "111",
    "me": "Nnah, ahh! Ugh... (Crap! Crap! It feels so gross\nwith pee!) (My panties are so heavy~!)"
  },
  { "No": "112", "me": "" },
  {
    "No": "113",
    "me": "Here are my briefs, please feel free to use them.\nDon't worry about getting them dirty. (Hehehe!\nWear them, young lady!) (Wear my briefs stained\nwith my dick juice!!)"
  },
  {
    "No": "114",
    "me": "Your briefs!?... They're too dirty!! Are you out\nof your mind!?..."
  },
  {
    "No": "115",
    "me": "Oh dear? Is that a no-go~? They're clean. Compared\nto that... skirt of yours that's emitting a foul\nodor... Gulp!"
  },
  { "No": "116", "me": "Ugh..." },
  { "No": "117", "me": "Will you change into this?" },
  { "No": "118", "me": "Give it to me!!..." },
  {
    "No": "119",
    "me": "Oh~ That looks good on you! It suits you well~\n(Bwahaha! Such a foolish young lady!) (Go ahead\nand stain my briefs with your pussy juice!)"
  },
  {
    "No": "120",
    "me": "This is my favorite towel, with this... Gulp!\nPlease cover up your important parts! Here you go.\n(Use it to cover up your slit, young lady!)"
  },
  {
    "No": "121",
    "me": "Just a towel!?... I can't do something so\nembarrassing! Don't make fun of me!"
  },
  { "No": "122", "me": "What's with this pattern~... Ugh..." },
  {
    "No": "123",
    "me": "Ahh~ Don't worry about it. (Bwahaha! It's like\nyour pussy is completely exposed!?) (Let the smell\nof your pussy soak into my towel! I'll savor the\nscent later!)"
  },
  {
    "No": "124",
    "me": "This one's a bit worn out, but it's still\nwearable. Here you go. (Hehehe! Please wear my\nunderwear, young lady!)"
  },
  {
    "No": "125",
    "me": "What the hell are you thinking! This is all\ntattered! Is this all you have!? (No! I can almost\nsee down there!)"
  },
  {
    "No": "126",
    "me": "That's all there is~ Please bear with it.\n(Giggling! What a view!) (I can almost see your\nnipples and slit! My dick is getting hard!)"
  },
  { "No": "127", "me": "Why do you have an apron ready!?" },
  {
    "No": "128",
    "me": "Ahh~ That looks great. It might be perfect for\nsomeone as flashy as you~ (Hehehehe! A high school\ngirl in a naked apron!) (What a stupid kid!\nGahaha!)"
  },
  { "No": "129", "me": "A swimsuit!? A school swimsuit!?... That's lewd!" },
  {
    "No": "130",
    "me": "Ah, what? That sounds bad~! This is, you know, for\nchanging! If you don't like it, fine! Stay as you\nare. Phew! Ahh, what's that smell~!"
  },
  { "No": "131", "me": "Grr! Give it to me!!" },
  {
    "No": "132",
    "me": "Ahh~ That's great! It seems to fit you perfectly.\n(Nhehehe! Let your body odor soak into it! I'll\nuse it for masturbation later!)"
  },
  {
    "No": "133",
    "me": "Here you go, a cardboard box. Use this to cover up\nthe front. (Kuhe~! Strip, come on, strip and cover\nup with the cardboard!)"
  },
  {
    "No": "134",
    "me": "You want me to cover up with this!?... You\npervert!... Perverted janitor!"
  },
  {
    "No": "135",
    "me": "It looks good~ It seems cool. No problem at all~.\n(Guhe~! Such a foolish girl!) (Almost completely\nnaked! Ass fully exposed! I can't stand it!)"
  },
  {
    "No": "136",
    "me": "Here you go, some newspaper. Use this to cover up\nthe front. (Kuhe~! Strip, come on, strip and cover\nup with the newspaper!)"
  },
  { "No": "137", "me": "" },
  { "No": "138", "me": "" },
  { "No": "139", "me": "" },
  { "No": "140", "me": "" },
  {
    "No": "141",
    "me": "Come this way, Akane Suzuki! It's your turn!\nPlease make it to the end safely~!"
  },
  {
    "No": "142",
    "me": "Come this way, Akane Suzuki! It's finally\nstarting! Please make it to the end safely~!"
  },
  {
    "No": "143",
    "me": "It's finally happening! I'm so excited... This...\nIt won't be boring, right!?"
  },
  {
    "No": "144",
    "me": "Eh? Of course not. I think you'll be quite\nsatisfied~ Mufufu! (My dick will be the one\ngetting satisfied!)"
  },
  {
    "No": "145",
    "me": "Nfuu~? Suzuki-san? Are you getting nervous by any\nchance? You're the only participant after all~\nGufufufu!"
  },
  {
    "No": "146",
    "me": "That's... That's not true at all! I'll do it!...\n(I... I might be scared... Ugh...)"
  },
  {
    "No": "147",
    "me": "(Muhahaha! Maybe I'll impregnate this cheeky young\nlady!)"
  },
  {
    "No": "148",
    "me": "Ah, right, right. Would you like something to\ndrink before we start? It seems everyone gets\nthirsty from the nerves. If you'd like... Gulp!"
  },
  { "No": "149", "me": "Then I'll take it..." },
  { "No": "150", "me": "" },
  {
    "No": "151",
    "me": "Hey~! Doesn't it smell?... I can't believe\neveryone stepped in poop on their way here~"
  },
  {
    "No": "152",
    "me": "Hey~! Doesn't it smell?... I can't believe there's\nsomeone who stepped in poop~"
  },
  {
    "No": "153",
    "me": "Ahh~ It definitely smells~... What animal's poop\ncould this be? Maybe it's human? Uhehehe! Just\nkidding!"
  },
  { "No": "154", "me": "Gross..." },
  { "No": "155", "me": "" },
  { "No": "156", "me": "" },
  { "No": "157", "me": "" },
  { "No": "158", "me": "" },
  { "No": "159", "me": "" },
  {
    "No": "160",
    "me": "Wh-What's going to come out!? No, no way! What is\nit, what is it!?"
  },
  { "No": "161", "me": "Wh-What's coming next!? I-I'm not scared at all!" },
  { "No": "162", "me": "Wh-What is this!?... I'm totally not scared at\nall!" },
  {
    "No": "163",
    "me": "Ugh, ugh... Wh-What's next!? Something's coming\nout!... Haa, haa!"
  },
  {
    "No": "164",
    "me": "Wait, is this for real!? Even I'm not scared!?...\nSo this was all it was...?"
  },
  {
    "No": "165",
    "me": "Haa, haa, this is the end, right!? I-I wasn't\nscared at all!..."
  },
  {
    "No": "166",
    "me": "Ha, ugh... I-I'm not scared, not scared at all!\nNo, no way!..."
  },
  {
    "No": "167",
    "me": "Haa~ I thought I might pee myself from fear and\nwore a diaper... To actually use it... Ahh~ It\nfeels gross..."
  },
  {
    "No": "168",
    "me": "Ah! There!? Hm!? I-I need to pee!... Are you\nserious right now!?..."
  },
  {
    "No": "169",
    "me": "Ah! There!? Hm!? My stomach hurts... Ouch! Why is\nthis happening!? Are you serious right now!?..."
  },
  { "No": "170", "me": "Uhihihi! Now, how shall I cook this young lady~?" },
  {
    "No": "171",
    "me": "What shall I torment her with next... I can't wait\nto shove my dick into this young lady~"
  },
  {
    "No": "172",
    "me": "Hmm... If I don't decide now, I won't be able to\ninsert my dick into this wicked young lady~..."
  },
  { "No": "173", "me": "" },
  { "No": "174", "me": "" },
  { "No": "175", "me": "How do you like the feel of these briefs~? Kuhii~!" },
  {
    "No": "176",
    "me": "Isn't this towel nice~? It's just like the young\nlady's pussy! Uhehehe~!"
  },
  { "No": "177", "me": "" },
  { "No": "178", "me": "Uhehehe! Come on, show me your flat chest!..." },
  { "No": "179", "me": "Let's see... Show uncle your slit... Gulp!" },
  { "No": "180", "me": "" },
  { "No": "181", "me": "Well, Suzuki-san, this seems to suit you..." },
  {
    "No": "182",
    "me": "Wh-Why do you have a bikini ready? Don't tell me\nit's the janitor's hobby or something!?"
  },
  {
    "No": "183",
    "me": "Ugh... Th-That's not it~ (This is a trophy from\nwhen I sneaked into the girls' dorm!...) (It's\nbeen a valuable piece of my jerk-off\ncollection...)"
  },
  { "No": "184", "me": "Ugh~ It's still kinda creepy~..." },
  {
    "No": "185",
    "me": "Huh!? Th-Then it's fine! Go ahead, keep it on.\nUgh, it smells! There's a smell around here!"
  },
  { "No": "186", "me": "Ugh! O-Okay, I get it! L-Lend it to me!..." },
  {
    "No": "187",
    "me": "Oh~ It looks good on you~ As expected of the\nyoung! It suits you~ (Uhihihi! Make sure to soak\nup the pussy smell!)"
  },
  { "No": "188", "me": "" },
  { "No": "189", "me": "More importantly..." },
  {
    "No": "190",
    "me": "You know, Yume Momono is kinda dangerous, right?\nShe's super precocious and a nympho, that's the\nrumor..."
  },
  {
    "No": "191",
    "me": "They say... she even tried to sneak into her dad's\nand brother's beds... Like, committing incest and\nstuff, right?"
  },
  {
    "No": "192",
    "me": "What!? Gulp! I hadn't heard such rumors~... (Oh,\nshe's just my type~?)"
  },
  { "No": "193", "me": "" },
  { "No": "194", "me": "" },
  { "No": "195", "me": "" },
  {
    "No": "196",
    "me": "But like, she's passed out cold! Ahahaha! It's,\nit's hilarious!... Gulp..."
  },
  {
    "No": "197",
    "me": "...So, like... Is Marimi okay?... She's not waking\nup..."
  },
  { "No": "198", "me": "Oh my~? Are you worried~? Hehehe..." },
  { "No": "199", "me": "I-It's not like that! I-I was just curious!..." },
  {
    "No": "200",
    "me": "I feel like I'm the only one left alive... (Isn't\nthis bad!? Am I going to faint too~!?)"
  },
  {
    "No": "201",
    "me": "I feel like I'm the only one left alive... (Isn't\nthis bad!? Why is everyone fainting~!?)"
  },
  { "No": "202", "me": "Gulp!... Akane-san... Are you scared~?..." },
  { "No": "203", "me": "Ahahaha!!" },
  { "No": "204", "me": "Eek! Don't make such a weird noise!!" },
  {
    "No": "205",
    "me": "Ah! S-Sorry! (Hehe! She seems pretty scared~! This\nmight be an easy win~!?)"
  },
  { "No": "206", "me": "So annoying-!!" },
  { "No": "207", "me": "" },
  { "No": "208", "me": "" },
  { "No": "209", "me": "" },
  { "No": "210", "me": "" }
]
