[
  {
    "No": "0",
    "me": "Ahahaha! Diapers with pantyhose!? ...And what's with this\nweird smell... Ew, that's filthy!"
  },
  {
    "No": "1",
    "me": "Ahahaha! I can smell the scent of poop coming from the\ndiaper! Gyahahaha!"
  },
  {
    "No": "2",
    "me": "Ahahaha! Ew, that's a filthy ass! The smell of poop is so\nstrong! Gyahahaha!"
  },
  {
    "No": "3",
    "me": "Ahahaha! The white coat is turning brown! ...Ew, that's\nfilthy!"
  },
  {
    "No": "4",
    "me": "Ahahaha! There's a brown stain on the skirt!! Ew, that's\nfilthy!"
  },
  {
    "No": "5",
    "me": "Ahahaha! The pantyhose are bulging with poop, you know!?\nGyahahaha!"
  },
  {
    "No": "6",
    "me": "Ahahaha! I can see the diaper through it! That's so\nexciting!"
  },
  { "No": "7", "me": "Ahahaha! The diaper is all wet! That's so exciting!" },
  { "No": "8", "me": "Ahahaha! Your thighs are all wet! That's so exciting!" },
  { "No": "9", "me": "Ahahaha! The skirt is wet with pee! Ew, that's filthy!" },
  {
    "No": "10",
    "me": "Ahahaha! The pantyhose are all wet! That's so exciting!"
  },
  { "No": "11", "me": "Ahahaha! The panties are all wet! That's so exciting!" },
  {
    "No": "12",
    "me": "You've had one kid and put on a bit of weight, haven't you,\nTokiko? Show me that body of yours! Uhehehehe!"
  },
  {
    "No": "13",
    "me": "The pussy of a married woman wasn't too bad either... It's\nrough compared to a high school girl, but... Guhahahaha!"
  },
  {
    "No": "14",
    "me": "The blowjob from a married woman wasn't too bad... It's\nrough compared to a high school girl, but... Guhahahaha!"
  },
  {
    "No": "15",
    "me": "Tokiko's anal wasn't too bad... It was reasonably tight...\nGuhahahaha!"
  },
  {
    "No": "16",
    "me": "Tokiko, I jerked off thinking about you... A married woman's\nbody is pretty good, buhahaha! Show me your body again!"
  },
  {
    "No": "17",
    "me": "Haa haa... Tokiko, take off your glasses for a bit...\nUhehehe!"
  },
  { "No": "18", "me": "Strip, Tokiko! Haa haa haa!" },
  { "No": "19", "me": "Tokiko! Give me back my shirt, strip! Strip! Haa haa!" },
  {
    "No": "20",
    "me": "Kukukuku! The naked apron suits you well, Tokiko! Hey, show\nme your tits too! Haa haa!"
  },
  {
    "No": "21",
    "me": "Buhahaha! Isn't it too small!? The school swimsuit must be\ndigging into your crotch! You can take it off, Tokiko!"
  },
  {
    "No": "22",
    "me": "Buhahaha! What a pathetic look, Tokiko! Take that off! You\nshould just be naked!"
  },
  { "No": "23", "me": "Hehehehe! Let's take it off, Tokiko... Gulp!" },
  {
    "No": "24",
    "me": "Haa haa haa! Take off your shirt, Tokiko... Show me your big\ntits..."
  },
  {
    "No": "25",
    "me": "Haa haa haa! Tokiko, take off your shoes... I'll smell them!\nGulp!"
  },
  {
    "No": "26",
    "me": "Tokiko!... Pantyhose!... Take them off and give them to me!\nHaa haa haa! I'll wrap my dick in your pantyhose!"
  },
  {
    "No": "27",
    "me": "Tokiko!... The bra, the bra!... Haa haa haa! Give it to\nme!... I can't stand it! My erection won't go down!"
  },
  {
    "No": "28",
    "me": "Tokiko... Haa haa haa! I can smell the lewd scent of an\nadult woman! Haa haa haa! I want to rub the crotch part on\nmy dick!"
  },
  {
    "No": "29",
    "me": "Tokiko... Haa haa haa! You pissed yourself, didn't you...\nHaa haa haa! Ah, I want to rub the crotch part on my dick!"
  },
  {
    "No": "30",
    "me": "Tokiko... Haa haa haa! You shit yourself, didn't you... Haa\nhaa haa! Ah, I want to rub the crotch part on my dick!"
  },
  {
    "No": "31",
    "me": "Tokiko... Haa haa haa! An adult like you wearing diapers...\nGulp! Ah, I want to smell it!"
  },
  {
    "No": "32",
    "me": "Tokiko... Haa haa haa! An adult like you wearing diapers and\nleaking... Gulp! Ah, I want to smell it!"
  },
  {
    "No": "33",
    "me": "Tokiko... Haa haa haa! An adult like you wearing diapers and\nshitting yourself... Gulp! Ah, it stinks!"
  },
  {
    "No": "34",
    "me": "Buhehehehe! Tokiko, don't you dare wear my briefs without\npermission! Give them back! You should just be bare pussy!"
  },
  {
    "No": "35",
    "me": "Buhehehehe! Tokiko, don't you dare use my towel without\npermission! Give it back! You should just be bare pussy!"
  },
  { "No": "36", "me": "Face the other way, Tokiko!" },
  { "No": "37", "me": "Face this way, Tokiko!" },
  {
    "No": "38",
    "me": "Huh!? Ah, ahh~ I'm sorry... I was just thinking... (That was\nclose, I got too absorbed...)"
  },
  { "No": "39", "me": "Muhehe~ A married woman's ass, gulp!" },
  {
    "No": "40",
    "me": "Um, Mr. Janitor... Are you okay? You've been staring at me\nfor a while... (Ew, this guy is really creepy...)"
  },
  { "No": "41", "me": "Uhehehe! You've got thick pubic hair, Tokiko~!" },
  { "No": "42", "me": "" },
  { "No": "43", "me": "" },
  { "No": "44", "me": "" },
  { "No": "45", "me": "I'm scared... My heart is pounding..." },
  {
    "No": "46",
    "me": "Huhuhu~ Was Ms. Watanabe always such a scaredy-cat~?\n(Muhehehe~ I bet her plump tits are jiggling with her\nheartbeat...)"
  },
  {
    "No": "47",
    "me": "Your husband is an English teacher, right~? Is it true what\nthey say? Were you getting cozy in the infirmary~?"
  },
  {
    "No": "48",
    "me": "Ha!? No, no, no way~! That's ridiculous! There's no way I\nwould do such a thing!"
  },
  {
    "No": "49",
    "me": "(Guh! Lies, all lies! I was the one who peeped at the scene\nin the infirmary!) (Damn it! That English teacher...)"
  },
  {
    "No": "50",
    "me": "By the way, teacher, it's about the students, you know, do\nyou have any idea what they might be afraid of? I want to\nmake it the ultimate test of courage..."
  },
  { "No": "51", "me": "Eh~ What they might be afraid of, huh... Well..." },
  {
    "No": "52",
    "me": "Ah, that girl, Yamada-san, who used to be in the track and\nfield club and went to the Inter-High. She got so nervous\nduring the real deal that she completely fell apart..."
  },
  {
    "No": "53",
    "me": "Because of that, she quit the club and used to come to the\ninfirmary a lot. She was almost neurotic, and maybe she\nbecame hypersensitive to the sound of crying..."
  },
  { "No": "54", "me": "Hohoho, the sound of crying, huh..." },
  {
    "No": "55",
    "me": "But since she started hanging out with Suzuki-san, she seems\nto have gotten a lot better. That's a relief."
  },
  { "No": "56", "me": "Ah, but Yamada-san isn't here, is she?" },
  {
    "No": "57",
    "me": "Teacher, I'm going to give you a real scare, so be prepared~\n(Ehehehe!)"
  },
  {
    "No": "58",
    "me": "Um... Please go easy on me... (No, his face is scary...)"
  },
  { "No": "59", "me": "" },
  {
    "No": "60",
    "me": "Mr. Janitor! It was really fun! The props were well made,\nyou must have worked hard on them in your free time~."
  },
  {
    "No": "61",
    "me": "Mr. Janitor! This is the best! I can see why the students\ntalk about it! The props were well made, you must have\nworked hard on them in your free time~."
  },
  {
    "No": "62",
    "me": "So, so you think... I'm glad you enjoyed it... (The image of\nmyself making props with an erection comes flooding back...\nSad! Damn it!!)"
  },
  { "No": "63", "me": "" },
  {
    "No": "64",
    "me": "Mr. Janitor, the props... They were well made. You worked\nhard... It was fun... Haa..."
  },
  {
    "No": "65",
    "me": "Ah, thank you... (Oh, she's totally looking down on me! On\nme!!) (Damn it, damn it!! It's too frustrating!!)"
  },
  { "No": "66", "me": "Haha, I'm sorry." },
  { "No": "67", "me": "So, you think so~... (Nngh~! She's mocking me!!)" },
  { "No": "68", "me": "" },
  { "No": "69", "me": "This content is so extreme... Are the students okay!?" },
  {
    "No": "70",
    "me": "Teacher, all the other students are laughing~ The only one\nwho fainted was... you, teacher~!"
  },
  {
    "No": "71",
    "me": "Eh!? Is that so!? Ah, I wasn't feeling well to begin with\ntoday... Mr. Janitor, about this... that..."
  },
  {
    "No": "72",
    "me": "Don't worry, I'll keep our promise. I won't tell anyone,\nabsolutely. (Uhehehe!)"
  },
  { "No": "73", "me": "No, I can't think of anything right now..." },
  { "No": "74", "me": "" },
  {
    "No": "75",
    "me": "This content is so extreme... Are the students okay!? (Ugh,\nthis is the worst! It's a good thing I was wearing a\ndiaper...)"
  },
  {
    "No": "76",
    "me": "Teacher, all the other students are totally fine~ They're\nall acting nonchalant. (How's the diaper holding up~?\nGuhehe!)"
  },
  {
    "No": "77",
    "me": "This content is so extreme... Are the students okay!? (Ugh,\nthis is the worst! It's a good thing I was wearing a\ndiaper...) (I can't believe I actually pooped myself!...)"
  },
  { "No": "78", "me": "" },
  {
    "No": "79",
    "me": "Eh!? Is that so!? Ah, I wasn't feeling well to begin with\ntoday... Mr. Janitor, about this... that..."
  },
  {
    "No": "80",
    "me": "This content is so extreme... Are the students okay!? (The\nstudents must be wetting themselves too, right!?...)"
  },
  {
    "No": "81",
    "me": "This content is so extreme... Are the students okay!? (I\ncan't believe I actually pooped myself!...) (The students\nmust be wetting themselves too, right!?...)"
  },
  {
    "No": "82",
    "me": "Teacher, all the other students are totally fine~ They're\nall acting nonchalant. The only one who ended up in this\nsituation was... well~ Uhehehe!"
  },
  {
    "No": "83",
    "me": "Stop that weird laugh, please! (This is so embarrassing, so\nembarrassing!!)"
  },
  {
    "No": "84",
    "me": "Um... Mr. Janitor, about tonight, please don't tell\nanyone... anyone at all... Haa haa haa!"
  },
  { "No": "85", "me": "" },
  {
    "No": "86",
    "me": "Teacher, all the other students are laughing~ The only one\nwho fainted was... you, teacher~! And you got... extremely\nwet, too."
  },
  { "No": "87", "me": "" },
  { "No": "88", "me": "Ahh... Ahh... (No, my stomach hurts...)" },
  { "No": "89", "me": "" },
  {
    "No": "90",
    "me": "Um, Mr. Janitor... I'm returning your briefs, it's too\nembarrassing to keep them..."
  },
  {
    "No": "91",
    "me": "Um, Mr. Janitor... I'm returning your towel, it's too\nembarrassing to keep it..."
  },
  {
    "No": "92",
    "me": "Ah, is that so... Then... you'll have to wear the wet\nclothes again, right. (Buhuhuhu! Go ahead and wear those\npiss-smelling clothes!)"
  },
  {
    "No": "93",
    "me": "Um, Mr. Janitor... I'm returning your shirt, it's too\nembarrassing to keep it..."
  },
  {
    "No": "94",
    "me": "Um, Mr. Janitor... I'm returning your apron, it's too\nembarrassing to keep it..."
  },
  {
    "No": "95",
    "me": "Um, Mr. Janitor... I'm returning your swimsuit, it's too\nembarrassing to keep it..."
  },
  {
    "No": "96",
    "me": "Um, Mr. Janitor... I'm returning your cardboard, it's too\nembarrassing to keep it..."
  },
  {
    "No": "97",
    "me": "Um, Mr. Janitor... I'm returning your newspaper, it's too\nembarrassing to keep it..."
  },
  {
    "No": "98",
    "me": "Ah, is that so... Then... you'll have to wear the dirty\nclothes again, right. (Buhuhuhu! Go ahead and wear those\nfilthy clothes!)"
  },
  { "No": "99", "me": "" },
  {
    "No": "100",
    "me": "Mmm, mmm, ahhhh... (A lukewarm thing is... clinging to my\ncrotch!) (It's dirty...!)"
  },
  {
    "No": "101",
    "me": "Mmm, mmm, ahhhh... (It's cold, so cold! My panties soaked\nwith pee are clinging to my crotch!) (It's dirty...!)"
  },
  { "No": "102", "me": "" },
  {
    "No": "103",
    "me": "Teacher, please use this! It was supposed to be my change of\nclothes for tonight, but I'll give it to you! (Wear it,\nTokiko! Get my briefs wet with your pussy juice!)"
  },
  {
    "No": "104",
    "me": "Eh!? Uh, Mr. Janitor... (Ew, that's gross...) You won't have\na change of clothes..."
  },
  {
    "No": "105",
    "me": "It's okay! I'm just so worried that you might be embarrassed\nabout the smell coming from your crotch! So please change!\nQuickly! Stinky!... Cough, cough! It's better if you change!"
  },
  { "No": "106", "me": "Eek! Yes, right away..." },
  {
    "No": "107",
    "me": "Ah, that's great, Teacher! So fresh, so fresh! The smell is\ngone! (Hehehe! I'll take those briefs later and wear them\nmyself) (and jerk off with them!)"
  },
  {
    "No": "108",
    "me": "Teacher, please use this! It's my favorite towel! (Hide it,\nTokiko! Cover your slit with that towel!)"
  },
  {
    "No": "109",
    "me": "Eh!? Uh, Mr. Janitor... (Ew, that's gross...) But it's your\nfavorite, isn't it?..."
  },
  {
    "No": "110",
    "me": "It's okay! I'm just so worried that you might be embarrassed\nabout the smell coming from your crotch! So take off the\ndirty one! And cover yourself with this! Quickly! Stinky!...\nCough, cough! It's better if you take it off!"
  },
  { "No": "111", "me": "It's pretty torn up though..." },
  {
    "No": "112",
    "me": "Ah, that's great, Teacher! It's hidden, it's hidden! The\nsmell is gone! (Hehehe! I'll wrap that towel around my cock\nlater) (and masturbate with it! Hehehe!)"
  },
  {
    "No": "113",
    "me": "Teacher, please, use my running shirt. Please use it. (Huff,\nhuff! Take it off, Tokiko! Take it off and wear my shirt!)"
  },
  {
    "No": "114",
    "me": "Eh!? Uh, Mr. Janitor... That's your change of clothes, isn't\nit... (Ew, that's gross...)"
  },
  {
    "No": "115",
    "me": "It's okay! I'm just so worried that you might be embarrassed\nbecause you leaked! So take off the dirty one! And change\ninto this! Stinky!... Ah, it smells! It's better if you take\nit off!"
  },
  {
    "No": "116",
    "me": "Ah, that's great, Teacher. (Gulp! Can't see your nipples,\ncan you!? Huff, huff!) (I can't stand it! My cock is rock\nhard!)"
  },
  { "No": "117", "me": "Eh!?... You mean, change into an apron!?" },
  {
    "No": "118",
    "me": "(Ah... I've only ever worn this kind of thing at home...\nIt's embarrassing...)"
  },
  {
    "No": "119",
    "me": "Ah, that's great, Teacher. (Gulp! I can barely see the bush!\nHuff, huff!) (I can't stand it! My cock is rock hard!)"
  },
  {
    "No": "120",
    "me": "Eh!?... A swimsuit!? I have to wear a school swimsuit!?\nThat's a bit..."
  },
  {
    "No": "121",
    "me": "It's tight... It's quite small... (Ouch, it's digging into\nmy crotch! Ouch...)"
  },
  {
    "No": "122",
    "me": "Ah, that's great, Teacher. (Hehe! It's digging in\neverywhere! Your breasts are about to) (pop out! I can't\nstand it! I'll masturbate with that school swimsuit later!!)"
  },
  {
    "No": "123",
    "me": "Teacher, this is just a temporary measure! Let's change into\nthis for now."
  },
  { "No": "124", "me": "This is... cardboard, isn't it!? Eh!?" },
  {
    "No": "125",
    "me": "Ah, that's great, Teacher. (Hehe! Your plump butt is\ncompletely exposed!) (Damn, I want to jerk off looking at\nyou!)"
  },
  { "No": "126", "me": "This is... newspaper, isn't it!? Eh!?" },
  {
    "No": "127",
    "me": "Teacher! Please bear with it! You smell because you leaked.\nI'm so worried that you might be feeling utterly humiliated!\nSo take off the dirty one! And change into this! Stinky!...\nAh, it smells! It's better if you take it off!"
  },
  { "No": "128", "me": "" },
  { "No": "129", "me": "" },
  { "No": "130", "me": "" },
  {
    "No": "131",
    "me": "Come this way, Tokiko Watanabe-san! It's your turn! Please\nmake it safely to the end!"
  },
  {
    "No": "132",
    "me": "Come this way, Tokiko Watanabe-san! It's finally time to\nstart! Please make it safely to the end!"
  },
  {
    "No": "133",
    "me": "It's finally happening... I'm so nervous about actually\ndoing a test of courage in a graveyard... It's too\nauthentic..."
  },
  {
    "No": "134",
    "me": "Is that so? Hehehe! Once you start walking through the\ngraveyard, you'll be even more thrilled! Make sure to keep\nyour spirits up! (Hehehe! I'm gonna do it! I'm gonna\nimpregnate a married woman!)"
  },
  {
    "No": "135",
    "me": "That's right, Teacher! How about a drink? Participants seem\nto get thirsty from the nerves... Would you like to have\nsome now? Gulp!"
  },
  { "No": "136", "me": "Yes, I suppose... I'll take it." },
  { "No": "137", "me": "" },
  { "No": "138", "me": "" },
  { "No": "139", "me": "" },
  { "No": "140", "me": "It stinks..." },
  {
    "No": "141",
    "me": "Yeah... Dog poop is quite potent, isn't it... Everyone\nstepping in it..."
  },
  { "No": "142", "me": "Yeah... Dog poop is quite potent, isn't it..." },
  {
    "No": "143",
    "me": "Ah, that's true... Dogs eat just about anything, so it\ndefinitely stinks... Hehehe!"
  },
  { "No": "144", "me": "" },
  { "No": "145", "me": "" },
  { "No": "146", "me": "" },
  { "No": "147", "me": "" },
  { "No": "148", "me": "" },
  { "No": "149", "me": "" },
  {
    "No": "150",
    "me": "Custodian-san, you really come alive during the test of\ncourage, don't you..."
  },
  {
    "No": "151",
    "me": "I heard it was scary... but it's still to come, isn't it...\nsurely..."
  },
  { "No": "152", "me": "Sa, Sasuga, it's a bit scary, isn't it... Gulp!..." },
  {
    "No": "153",
    "me": "Yo, Custodian-san, isn't this a bit too much... It's too\nscary..."
  },
  {
    "No": "154",
    "me": "It seems the rumors were a bit exaggerated... It's not scary\nat all."
  },
  {
    "No": "155",
    "me": "What's next!? Cho, Chotto, this is too scary... Are the\nstudents really enjoying this!?..."
  },
  {
    "No": "156",
    "me": "Hii! Higu!... Yo, Custodian-san~ Ko, Kowai... Haa haa! Ya,\nYarisugi yo this~ Ah, uuu..."
  },
  {
    "No": "157",
    "me": "Auu... O, Omutsu ga... It feels gross... I can understand\nhow babies feel..."
  },
  {
    "No": "158",
    "me": "Auu... O, Omutsu ga... It feels gross... I feel so\npathetic..."
  },
  {
    "No": "159",
    "me": "Auu... O, Omutsu ga... It feels gross... Isn't it over yet?\nCho, Chotto, I'm scared..."
  },
  {
    "No": "160",
    "me": "Uu... I don't want this, to feel the urge to go in a place\nlike this! What should I do..."
  },
  {
    "No": "161",
    "me": "Uu... O, Onaka ga... Ko, Konna tokoro de moyoosu nante! What\nshould I do..."
  },
  {
    "No": "162",
    "me": "Muhihihi~! Sensei~ Please faint during the next scare~!"
  },
  {
    "No": "163",
    "me": "Sensei~ Please faint next time, okay~? Otherwise, my dick is\ngoing to go crazy~ Guhehehe!"
  },
  {
    "No": "164",
    "me": "Sensei~! Please faint this time for sure~!... Yabee zo, I\nmust make it happen..."
  },
  { "No": "165", "me": "" },
  { "No": "166", "me": "" },
  { "No": "167", "me": "" },
  { "No": "168", "me": "Ahaha~ It's fine~ Tokiko, briefs suit you! Guhee~!" },
  { "No": "169", "me": "Uhehe! A plump married woman looks good in a towel~!" },
  { "No": "170", "me": "" },
  {
    "No": "171",
    "me": "Uhi~! Such plump breasts~! I want to caress them with my\ndick!"
  },
  {
    "No": "172",
    "me": "Buhehehe! Such thick pubic hair~! I want to splatter my\nsemen here~!"
  },
  { "No": "173", "me": "Choi to ass starting to sag, isn't it~? Buhahaha!" },
  { "No": "174", "me": "" },
  { "No": "175", "me": "Sensei, please use this! My bikini!" },
  { "No": "176", "me": "Hai!?" },
  {
    "No": "177",
    "me": "Ah! I mean, it's a supply from the school!... (That was\nclose!)"
  },
  {
    "No": "178",
    "me": "Would Sensei prefer a slightly more mature design? Ah, how\nabout this one!? Haa haa!"
  },
  {
    "No": "179",
    "me": "Ah, ano, such consideration isn't necessary!... (What's with\nthis person!...)"
  },
  { "No": "180", "me": "Hau... Ano! Cho, Chotto, this is!..." },
  {
    "No": "181",
    "me": "Aa~ That's good! It's better than wearing dirty underwear,\nright!? Isn't it~!? Gulp!"
  },
  { "No": "182", "me": "U, Uuu..." },
  { "No": "183", "me": "" },
  {
    "No": "184",
    "me": "Momono-san seems energetic~ I was worried because of the\nstrange rumors, but maybe she's mentally strong..."
  },
  { "No": "185", "me": "Ha? What do you mean?" },
  { "No": "186", "me": "Eh?... Na, Nanka iroiro uwasa ga atte..." },
  { "No": "187", "me": "Fuuun, rumors, huh~..." },
  { "No": "188", "me": "" },
  { "No": "189", "me": "" },
  { "No": "190", "me": "" },
  {
    "No": "191",
    "me": "If it's about Yamada-san... But she's resting in the temple\nnow..."
  },
  { "No": "192", "me": "Aa, is that so... (Tch!)" },
  { "No": "193", "me": "" },
  { "No": "194", "me": "" },
  { "No": "195", "me": "" },
  {
    "No": "196",
    "me": "I'm concerned about the child who fainted... Maybe I should\ngo check on her..."
  },
  {
    "No": "197",
    "me": "I'm concerned about the children who fainted... Maybe I\nshould go check on them..."
  },
  {
    "No": "198",
    "me": "Eh!? Eeto, Sensei... The lady of this temple... She said she\nwas a former nurse... We really owe her every time..."
  },
  {
    "No": "199",
    "me": "So no worries! Yup yup! Sensei, you should also enjoy\ntonight... and maybe faint... shall we~?"
  },
  {
    "No": "200",
    "me": "Yes!? No, no way~! It's not like adults faint or\nanything!... (No, I'm getting goosebumps...)"
  },
  {
    "No": "201",
    "me": "That's right~ Adults don't faint, do they~ Uho, uhohoho!"
  },
  { "No": "202", "me": "" },
  { "No": "203", "me": "" },
  { "No": "204", "me": "" },
  { "No": "205", "me": "" },
  { "No": "206", "me": "" },
  { "No": "207", "me": "" },
  { "No": "208", "me": "" },
  { "No": "209", "me": "" },
  { "No": "210", "me": "" }
]
