[
{"No":"0","me":"くへぇ～！\nいい眺めだねぇ～　女優のオムツ姿！\nひひひ！"},
{"No":"1","me":"うひひひ！\n全国区の女優の生尻だぜぇ～！\nはぁはぁ！"},
{"No":"2","me":"ひぃ～！\n漂うウンコ臭でめまいを起こしそうだぜぇ～！\nぐははは！"},
{"No":"3","me":"あぁ～　女優さんのお尻にウンコが付いちゃってるぜぇ～！\nみっともねぇなぁ～！\nぎゃははは！"},
{"No":"4","me":"むほぉ～！\n女優の失禁姿！　ヨダレが止めどなく溢れっちまうぜぇ～！\nはぁはぁはぁ！"},
{"No":"5","me":"うひぃ～！\nパンティもオシッコでびっちょりですなぁ～！\n恥ずかしいですなぁ～！　くへへへへ！"},
{"No":"6","me":"はぁはぁ～！\n可愛い尻！　股間から流れ出たオシッコの形跡がまた\n堪りませんなぁ～！　うへへへ！"},
{"No":"7","me":"ゴホッ～！\nこ、これが女優さんのウンコの香りかぁ～！\nぎゃははは！"},
{"No":"8","me":"ゴホッ　ゴホッ～！\n女優さんでもパンティにウンコしちゃう時が有るんだなぁ～\nぐへへへへ！"},
{"No":"9","me":"あぁ～　女優さんのお尻にウンコが付いちゃってるぜぇ～！\nみっともねぇなぁ～！\nぎゃははは！"},
{"No":"10","me":"オムツが重そうですなぁ～\nオジさんが交換してあげたいぐらいだよぉ～！\nゴクン！"},
{"No":"11","me":"おほぉ～！　これが女子校生女優のオマンコですかぁ～！？\n拭き取れていないオシッコを舐めまわしてぇ～！"},
{"No":"12","me":"くへぇ～！\n股間からウンコの臭いが漂ってますよ、吉浦さん！\n２年生にもなってまだオムツが取れませんかぁ！？\nうへへへへ！"},
{"No":"13","me":"くへぇ～！\n股間からウンコの臭いが漂ってますよ、吉浦さん！\nいけませんなぁ～　２年生にもなって～！\nうへへへへ！"},
{"No":"14","me":"スカートがオシッコで濡れちゃってますなぁ～！\nこんな姿、マスコミにバレたら大変ですなぁ～！\nぎゃははははは！"},
{"No":"15","me":"ひひひひひ！\n俺のブリーフを女優の吉浦美雪が穿いてるぜぇ～！\n一生もんのお宝だぜぇ～！"},
{"No":"16","me":"吉浦美雪の割れ目が俺のタオルにくっついてやがる～！\n後でチンポに巻きつけてオナニーせねば！\nうひひひひひ！"},
{"No":"17","me":"オシッコで湿った　おパンティ～！\nオマンコの匂いと相まって、さぞや香しい匂いを放っている\nんだろうなぁ～　くくく！"},
{"No":"18","me":"オシッコはちゃんと拭き取らないと、オマンコかぶれちゃう\nかもよぉ～！　はぁはぁはぁ！"},
{"No":"19","me":"スカートの下から漂う異臭、とても今を時めく女優さんの物\nとは思えませんなぁ～！\nぎゃははははは！"},
{"No":"20","me":"ひひひひひ！\n俺のブリーフを女優の吉浦美雪が穿いてるぜぇ～！\n一生もんのお宝だぜぇ～！"},
{"No":"21","me":"吉浦美雪の割れ目が俺のタオルにくっついてやがる～！\n後でチンポに巻きつけてオナニーせねば！\nうひひひひひ！"},
{"No":"22","me":"ウンコが付いちゃった　おパンティ～！\nそれどうすんの美雪ちゃぁん！\n捨てちゃうんだったらオジさんに売ってくれよぉ～！\n3000円で！　ぐへへへへ！"},
{"No":"23","me":"尻はちゃんと拭いたのかなぁ～！？\nウンコ付いてるとかぶれちゃうよぉ～！\nぎゃはははは！"},
{"No":"24","me":"ゴクリ！\nさてさて～　女子校生女優さんと着せ替えゴッコしちゃいま\nしょうかぁ～！\nぐひゃひゃひゃ！"},
{"No":"25","me":"ゴクリ！\n美雪ちゃぁ～ん、女子校生女優の美雪ちゃぁ～ん！\nお着替えゴッコして遊びまちゅかぁ～！？\nセックスした仲だからいいだろう～！？　ぐへぇ～！"},
{"No":"26","me":"ゴクリ！\n美雪ちゃぁ～ん！お着替えゴッコしまちゅかぁ～！？\n俺のチンポしゃぶりまくったんだからコレくらいいいだろう\n～！？　ぐへぇ～！"},
{"No":"27","me":"ゴクリ！\n美雪ちゃぁ～ん！お着替えゴッコしまちゅかぁ～！？\nアナルセックスした間柄なんだからコレくらいいいだろう\n～！？　ぐへぇ～！"},
{"No":"28","me":"ゴクリ！\n美雪ちゃぁ～ん！お着替えゴッコしまちゅかぁ～！？\n女子校生女優を目の前にオナニー…\n最高だったぜぇ～！　うけけけけ！"},
{"No":"29","me":"メガネなんか取っちゃいましょうねぇ～！"},
{"No":"30","me":"マスクなんか要らねぇだろう～！？"},
{"No":"31","me":"吉浦美雪の体臭が染み込んでる制服の上着…\nゴクン！\nぼ、勃起しちまうぜぇ～！"},
{"No":"32","me":"俺のシャツ、今晩着るんで返してくれや～\nうひひひひ！"},
{"No":"33","me":"エ、エプロン、俺のエプロン返してくれや～！\nぐふふふふ！"},
{"No":"34","me":"あぁ～！\n俺のスク水にオマンコ染み付けやがったなぁ～！？\n返せ！　ぐへへへへ！"},
{"No":"35","me":"女優がこんな　みっともない格好してちゃダメダメ！\n脱いじゃおうねぇ～！"},
{"No":"36","me":"はぁはぁはぁ！\n吉浦美雪のスカートっ！\nチンポ擦り付けて射精しまくりてぇ～！"},
{"No":"37","me":"うへへへ！　女優の脱ぎ立ての靴～！\nここにチンポ突っ込みてぇぜぇ～！"},
{"No":"38","me":"あぁ～！　いい匂いがしそうだぁ～！\nチンポに絡めてしごきてぇ～！　はぁはぁ！"},
{"No":"39","me":"くほほほ！\n女子校生女優のブラジャー！！\nはぁ～　乳のかほりが堪らんぜぇ～！"},
{"No":"40","me":"うひひひ！\n吉浦美雪の乳首を隠していた絆創膏ブラ～！\nビリっと取っちゃうよぉ～！"},
{"No":"41","me":"ひひひ！\n吉浦美雪のオマンコの匂いがするパンティーーー！！\n俺が頂くぜぇ！"},
{"No":"42","me":"ひひひ！\n吉浦美雪のパンティーーー！！\nすっかり汚れっちまってるなぁ～！\n俺が頂くぜぇ！"},
{"No":"43","me":"ひひひ！\n吉浦美雪のパンティーーー！！\n女優のウンコがくっついてやがるーー！\n俺が頂くぜぇ！"},
{"No":"44","me":"ひひひ！\n吉浦美雪が穿いたオムツ～！　オマンコとケツの匂いが染み\n込んでんだろうなぁ～！\nチンポくっつけてぇ～！"},
{"No":"45","me":"ひひひ！\n吉浦美雪が穿いたオムツ～！しかもウンコでほっかほか！\nひひひ！　チンポくっつけてぇ～！"},
{"No":"46","me":"ひひひ！\n吉浦美雪が穿いたオムツ～！しかもオシッコでほっかほか！\nひひひ！　チンポくっつけてぇ～！"},
{"No":"47","me":"ひひひ！\n吉浦美雪が穿いたオムツ～！しかもオシッコとウンコで\nほっかほか！\nひひひ！　チンポくっつけてぇ～！"},
{"No":"48","me":"はぁはぁはぁ！\nお、俺のブリーフを穿いた女子校生！…\n堪んねぇ～！　返せ～返してくれぇ～！\nぐはははは！"},
{"No":"49","me":"はぁはぁはぁ！\nあ、汗拭きてぇんだぁ～　俺のタオル！\n返せ～返してくれぇ～！\nぐはははは！"},
{"No":"50","me":"うへへへ！\nナプキンタイプのビキニ！　返してくれねぇか～！？\n俺の大事なコレクションなんだよぉ～！\nぎゃはははは！"},
{"No":"51","me":""},
{"No":"52","me":"美雪～！　ケツだケツ！\n後ろを向け！　はぁはぁ！"},
{"No":"53","me":"こっち向けよ美雪～！\nツラ見せろや～！"},
{"No":"54","me":""},
{"No":"55","me":"な、なんでしょう！？…　黙って見つめられると…\nちょっと…\n（うぅ～　ヤダヤダ　きもいよぉ～！）"},
{"No":"56","me":"は！…　あぁ～　あ、ちょっとボケっとしておりました！\n年ですかねぇ～　うは！　うはははは！！\n（やべぇ妄想の世界に漂いすぎたかぁ～！？）"},
{"No":"57","me":""},
{"No":"58","me":"お待たせしましたぁ～吉浦さぁん！\nアナタの番ですよぉ～！\n（女子校生女優のマンコを堪能してやるぜ～！）"},
{"No":"59","me":"はい！　頑張りますね！…\n（ちょっと緊張しちゃうな…）"},
{"No":"60","me":"道中なにが起きるか分かりませんが、どうか気を付けてゴール\nして下さいねぇ～！\nくれぐれも失神なされないように…　うくくく！"},
{"No":"61","me":"お、脅かさないで下さいよぉ～…\n（いやらしい表情浮かべてる！…　負けないわよ！）"},
{"No":"62","me":"あ、そうそう！\n参加者特典のドリンクサービスを忘れておりましたわぁ～\nどうです１本？　ぐびっと飲んで一気にゴールしませんか！？"},
{"No":"63","me":"ドリンク！？　そ、そうね…"},
{"No":"64","me":"それじゃ、頂こうかしら…"},
{"No":"65","me":"はいはい、くぅーっと飲んじゃって飲んじゃってぇ～！\n（えへへへへへ！）"},
{"No":"66","me":"ゴールは墓地の一番奥ですからね～！\nそれでは、いってらっしゃぁ～い！\n（うひぃ～！　犯すぞ　犯すぞぉー！！）"},
{"No":"67","me":""},
{"No":"68","me":""},
{"No":"69","me":""},
{"No":"70","me":"うう…　この辺って…　その、臭いですよね…"},
{"No":"71","me":"田舎ですからぁ、女優さんには縁遠い匂いでしょうねぇ～\nうくくくっ！"},
{"No":"72","me":"わ、私が最後の一人…　ゴクン…\n失神する人が出るなんて…　うう…"},
{"No":"73","me":"あれれ？　あれぇ～？\nどうしたんですかぁ？　まさか有名女優の吉浦美雪さんが\nビビってる訳じゃぁないですよねぇ～？　まさかね…\nうひゃひゃひゃ！"},
{"No":"74","me":"えぇ～！　ま、まさかっ！…\nへ、平気ですっ　こんな状況よりももっと緊張する場面は\nいくつも経験しましたからっ！…　ゴクン…"},
{"No":"75","me":"そうですかそうですか、それは心強いですなぁ～\n（い、意外と手強いのか！？…）"},
{"No":"76","me":"参加者が私一人だったなんて、ちょっぴり緊張しちゃうかな…\n（やだぁ～　こんなオジさんと墓場で２人だけだなんて…）\n（変な事されたら　どうしよっ…）"},
{"No":"77","me":"さすがの女優さんでも緊張しちゃいますかぁ！？\nうへっ！　うへへへ～！\nでもでもぉ～　面白いから気楽に楽しんじゃって下さいよ～！"},
{"No":"78","me":"準備出来次第、始めますからねぇ～！"},
{"No":"79","me":"は、はい…\n（こ、この人　１人で盛り上がってるみたい…）"},
{"No":"80","me":"いやぁ～　こんな間近に現役女子校生のキレイな女優さんと\n一緒にお話出来るなんて、オジさん幸せですよぉ～！\n興奮しちゃうぅ～！　うへへへ！\n（抱いてやっからなぁ～　犯しまくってやんぜぇ～！）"},
{"No":"81","me":"まぁ、奇麗だなんて…\n（はぁ、何なのよ何なのよ～！　私を知らないだろうから）\n（気楽に出来ると思ってたのにっ！　早速バレるなんて…）\n（これが有名女優のサガなのねぇ…）"},
{"No":"82","me":"最近出した写真集もすごく売れたみたいですねぇ～\nかくいう私も恥ずかしながら写真集買っちゃいましたよぉ～！\n3000円でしたっけぇ～？"},
{"No":"83","me":"え！？　用務員さんも！？\n（やだキモいぃ…）"},
{"No":"84","me":"中々キワどいポーズのオンパレードで、女子校生なのに\nいいのかよオイオイ！って感じで～！　うへぇ～～！！\n（見ながらオナニーしまくったぜぇ～！）\n（おかげで写真集パリパリ！　ぶはははは！！）"},
{"No":"85","me":"し、仕事ですから…\n喜んで下さるファンの方たちの為もは、身を粉にして頑張る\nだけです…"},
{"No":"86","me":"（あぁ～　なんて偉大なの私ったら！きっとこの用務員さん）\n（が学園中に言いふらすハズよ、私の素晴らしさを！）\n（私のけなげさを！　あはははは！）"},
{"No":"87","me":"（うひぃ～！　写真集で見た身体を、実物を犯す大チャンス）\n（だぜぇ～！　有名現役女子校生女優の身体を！！）\n（ぶはははは！）"},
{"No":"88","me":"よ、吉浦さんっ！…　は、早くヤりたいでしょ！？\nね？　ねぇ～！？　はぁはぁ！"},
{"No":"89","me":"え！？　えぇ　そ、そうですね！\nやりたいです！　早くやりたいなぁ～　うふふ…\n（な、なんか興奮してる　この人…）"},
{"No":"90","me":"オジさんも早くヤりたいですっ！\n準備できたら　お声おかけしますね！　はぁはぁ！"},
{"No":"91","me":"は、はいぃ…"},
{"No":"92","me":""},
{"No":"93","me":"用務員さん、楽しかったです。\nいい気分転換が出来ましたよ、有難うございます。"},
{"No":"94","me":"楽しかった～！　用務員さん有難うございました！\nお陰で　いい気分転換が出来ました！"},
{"No":"95","me":"そうですかぁ～　う、嬉しいですよぉ～\n有名な女優さんに　そんな事言ってもらえるなんて…\n（クソォー！　逃がした魚がデカ過ぎるぞぉー！！）"},
{"No":"96","me":"そんな有名だなんて…\n子役上がりだからって、まだまだバカにされる事が多くて…"},
{"No":"97","me":"用務員さんのお陰でリフレッシュ出来たんで、これからも\n頑張りますね！"},
{"No":"98","me":"そ、そうですかぁ…　応援してますよ～　吉浦さんっ…\n（ううっ　チキショウ～！）"},
{"No":"99","me":""},
{"No":"100","me":"あ、ゴメンなさい！\n転校して来たばかりじゃ分かりませんよねぇ～…\n（うぅ～む…）"},
{"No":"101","me":""},
{"No":"102","me":"よ、用務員さん…　楽しかったですよ…\n大変でしたよね…　色々と小道具を準備されていたようで…\n（あぁ～　なんだかイライラするっ…）"},
{"No":"103","me":"そ、そうですかぁ～？　う、嬉しいですよぉ～\n有名な女優さんに　そんな事言ってもらえるなんて…\n（クソォー！　逃がした魚がデカ過ぎるぞぉー！！）"},
{"No":"104","me":"うっ！…\n（この程度の事で喜んでるのこの人！？…）\n（なんでこんなのに参加しちゃったんだろ！）\n（自分が情けなくなって来る！…）"},
{"No":"105","me":"こ、これからも頑張って下さいね～…"},
{"No":"106","me":"そ、そうですかぁ…　応援してますよ～　吉浦さんっ…\n（ううっ　チキショウ～！）"},
{"No":"107","me":"き、気持ち悪いっ…\n（こ、股間がぁ～　くっちょりしてて気持ち悪いよぉ～）"},
{"No":"108","me":"ん！？　ど、どうしましたぁ～！？\nご気分でも！？\n（ぶへへへ～！）"},
{"No":"109","me":"あ！　いいえぇ～　だ、大丈夫ですっ…\n（オムツを穿いてたから良かったけど、やっぱり気持ち）\n（悪いっ…）"},
{"No":"110","me":"（むひひひ！）\n（オムツの中はオシッコでグッショリなんだろう～？）\n（妄想しただけでチンポがガッチガチになっちまうぜぇ～！）"},
{"No":"111","me":"（むひひひ！）\n（オムツの中はウンコでズッシリなんだろう～？）\n（妄想しただけでチンポがガッチガチになっちまうぜぇ～！）"},
{"No":"112","me":"（むひひひ！）\n（オムツの中はオシッコとウンコでグチョグチョなんだ）\n（ろう～？）\n（妄想しただけでチンポがガッチガチになっちまうぜぇ～！）"},
{"No":"113","me":"な、何よ　ほっといてよぉ！…\nいちいち構わないでっ！　内緒にしてくれるハズでしょ！？"},
{"No":"114","me":"いやぁ～　アソコが気持ち悪いんだなぁ～\nなんて思いましてねぇ～\nぐふふふ！"},
{"No":"115","me":"いやぁ～　ウンコで気持ち悪いんだなぁ～\nなんて思いましてねぇ～\nぐふふふ！"},
{"No":"116","me":"シッ！　シッーーーーー！！！"},
{"No":"117","me":"まぁまぁ、あのぉ～　良ければなんですがね…\nお着物…　着替えちゃいますかぁ？　ゴクン！"},
{"No":"118","me":"え！？　着替え！？…"},
{"No":"119","me":""},
{"No":"120","me":"まさか学園の出し物で失神しちゃうなんて…\nあり得ないよぉ～…"},
{"No":"121","me":"（あっ！…　あれ！？　お、お腹がなんか痛い…）\n（な、なんで！？　え！？　なんでよ！？）"},
{"No":"122","me":""},
{"No":"123","me":"吉浦さぁ～ん　大丈夫ですか～？\nいやぁ～　見事に失神しちゃいましたからねぇ～！\nステ～ンって、ステ～ンって見事に。　うへっ"},
{"No":"124","me":"ちょ、ちょっと声大きいって！\n用務員さん本当に秘密守れるの！？　約束したでしょ！？"},
{"No":"125","me":"は！？　そうでしたそうでした！\nついウッカリぃ～　うへへへ！\n大丈夫、オジさんを信じてぇ～！"},
{"No":"126","me":""},
{"No":"127","me":"はうっ！…\n（ま、またお腹がっ…　キュルキュル鳴ってるっ…）"},
{"No":"128","me":"おんやぁ～？\nどうしましたぁ～？　失神、しちゃったせいで具合でも？\n失神したから、かなぁ～？…"},
{"No":"129","me":""},
{"No":"130","me":"まさか学園の出し物が　こんなにも怖い物だったなんて…\n知ってたら絶対来てないよぉ～…\nま、まだ体が震えてる…"},
{"No":"131","me":"（いひひひ！　身体が小刻みに震えてやがるぜぇ～）\n（トラウマになっちまったかなぁ～？）"},
{"No":"132","me":"（女優さんがオムツ穿いて、オシッコしちゃってんだもん）\n（なぁ～　傑作だぜぇ～　ぐへへへへ！）"},
{"No":"133","me":"（女優さんがオムツ穿いて、ウンコしちゃってんだもん）\n（なぁ～　傑作だぜぇ～　ぐへへへへ！）"},
{"No":"134","me":"（女優さんがオムツ穿いて、オシッコやらウンコやら）\n（モリモリしちゃってんだもんなぁ～　傑作だぜぇ～）\n（ぐへへへへ！）"},
{"No":"135","me":"吉浦さぁん、大丈夫～？　大事な女優さんなのに　驚かせ\n過ぎちゃって…"},
{"No":"136","me":"しかも…　へへ、オシッコ…　漏らしたしねぇ～…"},
{"No":"137","me":"しかも…　へへ、ウンコ…　漏らしたしねぇ～…"},
{"No":"138","me":"しかも…　へへ、オシッコやらウンコやら一杯…\n漏らしたしねぇ～…"},
{"No":"139","me":""},
{"No":"140","me":"あぁ～！　そうだそうだ！\n着替えが有るんですよ～　選び放題の着替えが～　ゴクン！\nそんな汚れた服を女優さんが着てちゃダメでしょう～…"},
{"No":"141","me":""},
{"No":"142","me":"いやぁ～　有名女優さんなのにバラエティのタレントさん\nみたいな姿になっちゃいましたねぇ～"},
{"No":"143","me":"わ、私はタレントじゃないわよ！　女優よ　女優ー！"},
{"No":"144","me":"は！…　ご、ごめんなさい…\n大声出しちゃって…　ううっ…"},
{"No":"145","me":"あはぁ～　いいんですよぉ～　慣れてますからぁ～"},
{"No":"146","me":"（あっ！…　あれ！？　お、お腹がなんか痛い…）\n（な、なんで！？　え！？　なんでよ！？）"},
{"No":"147","me":"（この私が、この年で　ウ、ウンコ漏らすなんてっ…）\n（信じられないよぉーっ…）"},
{"No":"148","me":"（むほほほ～！）\n（おそそ　してしまった事が相当堪えているようだなぁ～！）\n（女優のウンコの臭いが漂ってるぜぇ～！）"},
{"No":"149","me":"（この私が、この年で　も、もも、漏らすなんてっ…）\n（信じられないよぉーっ…）"},
{"No":"150","me":"（むほほほ～！）\n（おそそ　してしまった事が相当堪えているようだなぁ～！）\n（女優としてのメンツ丸つぶれだなぁ～～！）"},
{"No":"151","me":""},
{"No":"152","me":"う、うう、ヒドイ…　こんな着替えだなんて…\n（こ、これでも私　女優よ！？…　こ、この格好っ…）\n（よ、よそではとても見せられないっ…　ううっ…）"},
{"No":"153","me":"う、うう、ヒドイ…　タオルで隠すだなんて…\n（こ、これでも私　女優よ！？…　こ、この格好っ…）\n（よ、よそではとても見せられないっ…　ううっ…）"},
{"No":"154","me":"う、うう、ヒドイ…　これナプキンじゃないの！？…\n（こ、これでも私　女優よ！？…　こ、この格好っ…）\n（よ、よそではとても見せられないっ…　ううっ…）"},
{"No":"155","me":"あれ！？　なんか嫌そうですねぇ～？\nやっぱ女優さんとかお高くとまってる感じだから、庶民の\n気遣いとか分かんないんだろうなぁ～…"},
{"No":"156","me":"それじゃ、元の汚い制服をまた着ますぅ～？"},
{"No":"157","me":"う、うう、ヒドイ…　オジさんのシャツ１枚だけだなんて…\n（こ、これでも私　女優よ！？…　こ、この格好っ…）\n（よ、よそではとても見せられないっ…　ううっ…）"},
{"No":"158","me":"う、うう、ヒドイ…　これって裸エプロン！？…\n（こ、これでも私　女優よ！？…　こ、この格好っ…）\n（よ、よそではとても見せられないっ…　ううっ…）"},
{"No":"159","me":"う、うう、ヒドイ…　なんでスクール水着　着てるの！？…\n（こ、これでも私　女優よ！？…　こ、この格好っ…）\n（よ、よそではとても見せられないっ…　ううっ…）"},
{"No":"160","me":"う、うう、ヒドイ…　これ何かの役を演じてるの！？…\n（こ、これでも私　女優よ！？…　こ、この格好っ…）\n（よ、よそではとても見せられないっ…　ううっ…）"},
{"No":"161","me":"う、うう、ヒドイ…　絆創膏にナプキン！？　何よ！？…\n（こ、これでも私　女優よ！？…　こ、この格好っ…）\n（よ、よそではとても見せられないっ…　ううっ…）"},
{"No":"162","me":"え！？　べ、別にお高くなんてっ…\n（これが気遣い！？　そうなの！？…）\n（これが庶民感覚なの！？…）"},
{"No":"163","me":""},
{"No":"164","me":"はっ…　ああぁぁっ…　う、ううっ…\n（ウ、ウンコがっ…　ウンコが当たるぅ～！！！）"},
{"No":"165","me":"はっ…　ああぁぁっ…　う、ううっ…\n（こ、股間がぐちょぐちょしてるよぉ～！！！）"},
{"No":"166","me":""},
{"No":"167","me":"んほぉ～…\nささ、どうぞぉ～　私の愛用しているブリーフですが。\nおろしたてなので安心して下さい（ウソウソ）。"},
{"No":"168","me":"ひぇっ！？　よ、用務員さんの！？…　ウソ！？"},
{"No":"169","me":"汚れた制服より…　いいんじゃないですかぁ～？\nうへへへ！"},
{"No":"170","me":"こ、これホントに新品？…\nなんだか染みが付いてるような…"},
{"No":"171","me":"うけぇーーー！！！\nあぁ～　さすが女優ー！　なんーでもっ似合う！！　いい！！\n（おひょひょひょ！　俺の宝が増えたぜぇ～！！）"},
{"No":"172","me":"んほぉ～…\nささ、どうぞぉ～　まぁいタオルですが。\nこれで大事なアソコちゃんを隠してくだしい！…\nぶふふふっ！…"},
{"No":"173","me":"ひぇっ！？　ウソでしょ！？　タオルで隠せって！？\n冗談でしょ！？…"},
{"No":"174","me":"あぁ～　吉浦さん…　そんな恰好のままだと、まるで漏らし\nたかのように見られちゃいますよ～…\n全国区の女優さん…"},
{"No":"175","me":"ううっ…"},
{"No":"176","me":"んほぉ～…\nささ、どうぞぉ～　最新のビキニでーす！\nこれに着替えれば、誰もアナタが漏らしたなんて思いません\nよ～！　ぶふふふっ！…"},
{"No":"177","me":"ひぇっ！？　ビ、ビキニ！？　マ、マジで！？…"},
{"No":"178","me":"あ、ああぁぁ…\n（これナプキンじゃないのぉ！？）"},
{"No":"179","me":"これこれ吉浦さん！\nこのシャツきっとアナタにお似合いですよ！\nはぁはぁ！　私のですが！\nちゃぁんと洗濯してますから安心して（ウソウソ）。"},
{"No":"180","me":"ひぇっ！？　よ、用務員さんの！？…　ウソ！？\n（き、気持ち悪っ！！）"},
{"No":"181","me":"こ、このシャツ…　よれよれで伸びてますけど…"},
{"No":"182","me":"これこれ吉浦さん！\nこのエプロンきっとアナタにお似合いですよ！\nはぁはぁ！"},
{"No":"183","me":"え？　エプロン！？…　なんで！？…"},
{"No":"184","me":"いやっ…　ちょ、ちょっとエッチじゃないですか！？\nみ、見ないで下さいっ…"},
{"No":"185","me":"うけぇーーー！！！\nあぁ～　さすが女優ー！　なんーでもっ似合う！！　いい！！\n（おひょひょひょ！　俺の宝が増えたぜぇ～！！）"},
{"No":"186","me":"これこれ吉浦さん！\n学園の備品なんですけどね…　スクール水着～！　へへ！\n（マイコレクションでぇーす！）\n（股間部分で何度もオナりましたわぁ～！）"},
{"No":"187","me":"え？　スクール水着！？…　水着ですかぁ～！？"},
{"No":"188","me":"き、きき、着てくだしい！　ゴクン！"},
{"No":"189","me":"よ、用務員さん…\n（この人、気持ち悪すぎぃ…）"},
{"No":"190","me":"ピ、ピッタリですけど…　なんで墓場でスクール水着！？…\n恥ずかしいよぉ…"},
{"No":"191","me":"吉浦さ～ん、これでしのいでみますか！？　段ボール！\n意外と温かいんですよぉ～！　はぁはぁ！"},
{"No":"192","me":"え？　段ボール！？…　段ボール！？\n何言ってるの！？\nそ、それをどうするんですか！？"},
{"No":"193","me":"巻くんです。"},
{"No":"194","me":"ちょ、ちょっと過激ですよ　これ～…　うう…\n恥ずかし過ぎるっ…"},
{"No":"195","me":"吉浦さ～ん、汚れた制服よりキレイな新聞紙！\n今日の朝刊ですから安心です！"},
{"No":"196","me":"え？　新聞！？…　新聞！？\nそれをどうするんですか！？"},
{"No":"197","me":"吉浦さ～ん、アナタにおススメの素敵なビキニ！\n来年の新作らしいですよぉ～！"},
{"No":"198","me":"え？　ビキニ！？…　ここでビキニ！？\nえぇ～～～…"},
{"No":"199","me":"臭く汚れきった制服か、清潔なビキニか。\nどちらがいいと思います？　全国区の女優さん…"},
{"No":"200","me":"ちょ、ちょっと過激ですよ　これ～…　うう…\n絆創膏と…（ナ、ナプキン！？）\n恥ずかし過ぎるっ…"},
{"No":"201","me":""},
{"No":"202","me":""},
{"No":"203","me":"ゴクン！…\nこ、ここで何かあるの！？\nやだっ　鳥肌立っちゃいそう…"},
{"No":"204","me":"肝だめしドキドキするなぁ♪　何が出てくるんだろう♪"},
{"No":"205","me":"あぁ～　また何かで驚かそうっていうのね…\n今度はなぁに？"},
{"No":"206","me":"次はどんなの出てくるの！？　ん～　ドキドキするぅ～！"},
{"No":"207","me":"こ、今度は何出てくるの！？…　うう、何だか寒気が…"},
{"No":"208","me":"これで終わりかしら？　もう早くやっちゃって。\nなんだか退屈して来ちゃった。"},
{"No":"209","me":"今度は何！？　何で驚かせてくれるの！？\n早く早く～！"},
{"No":"210","me":"こ、これで終わりよね！？　さ、寒いよぉ…\nうう、ビクビクしてる…　こ、怖いっ…"},
{"No":"211","me":"あうぅっ…　まさかオムツを使う事になるなんて…\n気持ち悪いよぉ…"},
{"No":"212","me":"た、楽しいけど漏らしちゃう程ビックリするなんて…\n甘く考えすぎてた～…"},
{"No":"213","me":"うう、オムツ気持ち悪いよぉ～　ぐちゅぐちゅしてるぅ…"},
{"No":"214","me":"んあっ…　やだっ…　オ、オシッコしたい…"},
{"No":"215","me":"い、痛っ…　お、お腹が…　あうっ…\nど、どうしよぉ！？　いたたた…"},
{"No":"216","me":"さぁて、どの道具で驚かせてやろうか～！？\nビックリしてぶっ倒れてくれよぉ～！"},
{"No":"217","me":"へへへ！　吉浦美雪～！\n次の道具で失神しろよぉ～！\nそしてオジさんと気持ちいい事しようなぁ～！"},
{"No":"218","me":"み、美雪～！　次の道具で失神しろよ～！\n頼むっからさぁ～！　オジさん射精してぇんだよぉ～！"},
{"No":"219","me":""},
{"No":"220","me":""}
]