[
{"No":"0","me":"んのぉっ！！！"},
{"No":"1","me":"Yikes!\nI just peed my pants!\nオシッコで出ちゃったヨー！…　ううっ…"},
{"No":"2","me":"Yikes!\nI've got a shit!\nウンコ出ちゃったヨー！…　ううっ…"},
{"No":"3","me":"うひひ、うひひぃ～～！！\nモリィ～！　オシッコしかぶりやがったぞ！！\nうほほほほほー！！"},
{"No":"4","me":"うひひ、うひひぃ～～！！\nモリィ～！　ウンコしやがったぞ！！\nうほほほほほー！！"},
{"No":"5","me":"No~... this is... boring...\nツマらないネぇ～…"},
{"No":"6","me":"あららららぁ…\nBummer.\nI'm not scared at all..."},
{"No":"7","me":"Oh! ...\nチョット、コワかったデスねぇー！…\nビックリしたヨ～…"},
{"No":"8","me":"Great!\nYou scared the shit out of me!\nオドロきましたー！"},
{"No":"9","me":"チョ、チョット！…　コワすぎましたぁー…\nScary, scary, scary..."},
{"No":"10","me":"No!　It's not good!　I can't stand it! ...\nコワすぎデス、デスねー！…"},
{"No":"11","me":"イエェ～イ！　いえす　いえぇ～す！\nオジさんハッピィー！　超ハッピィ～！\nヤりました！\n黒人女子校生、失神させちゃいましたぁー！"},
{"No":"12","me":""},
{"No":"13","me":"ひぐっ！！！…"},
{"No":"14","me":"アレ！？　アレ！？…\nЯ описался! ...\nオシッコ…　でちゃったヨォ…"},
{"No":"15","me":"ヤバいっ！　ヤバいネ！…\n（Я обосрался! ...）\nウ、ウウ、ウンコがぁ…"},
{"No":"16","me":"ぶひひ　ぶひひ！～\nオルガちゃん　立ったまんま、オシッコ漏らしちゃった\nねぇ～！　はぁはぁはぁ！"},
{"No":"17","me":"おほぉ～！\n出ちゃったねぇー！　オルガちゃん、立ちウンコ！！\n器用なロシア娘だぜぇ～！　ぎゃははは！"},
{"No":"18","me":"あぁ～　コレはガッカリですネェ…\nオモシロくないネェ～…"},
{"No":"19","me":"Это скучно.\nコワくないヨ、全然ネェ…"},
{"No":"20","me":"Сюрприз!\nおぉ～　驚いたネェ～！　ちょと、ドキドキ！"},
{"No":"21","me":"Мне страшно!\n怖かったですネェー！　ちょと汗ばんだヨォ～！"},
{"No":"22","me":"Мне слишком страшно!\nちょと、コレ　ヤバですよぉー！\nはぁはぁはぁ！"},
{"No":"23","me":"О нет!\nダメね　コレ　ダメねぇー！　コワい　コワいですー！"},
{"No":"24","me":"うきょぉー！　やった　やったぜぇー！\nロシア娘を失神させちゃったー！\nくぅ～～！！"},
{"No":"25","me":""},
{"No":"26","me":"あうっ　あっ　あっ！"},
{"No":"27","me":"うぐっ…　ああぁぁ…　はぁあぁ…\nデ、デチャったぁぁぁ…　あぁぁぁ…"},
{"No":"28","me":"うぐっ…　ああぁぁ…　はぁあぁ…\nウンコしちゃったぁぁ…　あぁぁぁ…"},
{"No":"29","me":"ぐふふふ！\nアッチャラ～　オシッコ漏らしちゃったねー！\nひひひひ！"},
{"No":"30","me":"ぐふふふ！\nアッチャラ～　ウンコが出ちゃったみたいだねー！\nひひひひ！"},
{"No":"31","me":"ブア…\nナンですかぁ…　ふぅ～…"},
{"No":"32","me":"うぅ～ん…　くだらないデェス…"},
{"No":"33","me":"やだっ　フゥー　こわかったネ！\nコワイでしたぁ～！"},
{"No":"34","me":"ウゥー！　ビックリね！　ビックリだよぉー！\nあはははは！"},
{"No":"35","me":"オォォ！　あっ　あっ…\nダメね、ノォノォー　これコワイっ…"},
{"No":"36","me":"うぅーー！　コワイです　コワイですー！\nヤメテくださィ！…"},
{"No":"37","me":"よっしゃぁー！\nタ、タイの女子校生を　失神に追い込んだぞぉー！"},
{"No":"38","me":""},
{"No":"39","me":"うっ　ぐぅっー！！"},
{"No":"40","me":"のっ　のぉぉっ…\nヤバァい…　オシッコでたねぇ…　あぁぁ…"},
{"No":"41","me":"うぐあぁぁっ…\nで、出たよぉ…　ウ、ウンコぉ　出たよぉ！…\nはぁはぁはぁ！"},
{"No":"42","me":"あらぁ！　やっちゃった！\nやっちゃったね　アッチャン！　くくく！"},
{"No":"43","me":"うひひひ！\nアッチャン　ウンコブリブリ出ちゃったみたいだねぇ～！\nぐひゃひゃひゃひゃ！"},
{"No":"44","me":"………………"},
{"No":"45","me":"マイサヌック…\nダメですネ…　ふぅ…"},
{"No":"46","me":"フフフ！\n楽しいー！　オモシロいデス！\nいいネ！　いいネ！"},
{"No":"47","me":"ビックリしましたー！　驚いたデス！\nくふふふ！"},
{"No":"48","me":"こ、これ…　ムリね…　コワすぎですヨォ！\nはぁはぁ…"},
{"No":"49","me":"あああ…\nコワイですー！　あっ　あっ　あっ…"},
{"No":"50","me":"おほほ、おほほぉ～い！\nタイの女子校生ゲット～ぃ！！\n俺のチンポ臨戦態勢だぜぇ～！！"},
{"No":"51","me":""},
{"No":"52","me":""},
{"No":"53","me":""},
{"No":"54","me":"ひひひっ…　さすがアメリカ人…　図体デカいぜぇ～\nだが俺にとっちゃぁ、女子校生…\n性欲対象の女子校生！　国籍なんぞ関係ねぇ！\n白人だろうが黒人だろうが、肌の色で差別はしねぇぞぉ～！"},
{"No":"55","me":"へへへ！　次　キメてやんぜぇ～！\n卒倒させて、日本のチンポをねじ込んでやっからなぁ～！"},
{"No":"56","me":"ん～！　焦るな俺～！…\n次は失神する！　確実にこの黒人娘は失神する！\nそんでマンコに俺のチンポをっ…　はぁはぁはぁ！"},
{"No":"57","me":"オムツ使った感想は～！？　ひひひ！\n異国の地でオムツを　実際に使うとはなぁ～！\n傑作だぜぇ～！"},
{"No":"58","me":""},
{"No":"59","me":"くへぇ～　透き通るような白い肌っ…\n貪りつきてぇ～　精液ぶちまけてぇ～！\nはぁはぁ、失神させるぞぉ～！"},
{"No":"60","me":"次は思いっきりビビらせてやんぜぇ～！\n失神しろよ、失神～！\nそうじゃねぇと、チンポが勃起し過ぎて痛ぇんだよ～！"},
{"No":"61","me":"ヤベぇ、ラストチャンスかよ…\nロシア人のオマンコに　生挿入する機会を逃してしまうっ…\n頑張らねばっ…"},
{"No":"62","me":"むひぃ～　オムツの感触はどうかな～？\nそのまま付けてると、白いお尻が被れちゃうかもよぉ～\nうへへへへ！"},
{"No":"63","me":""},
{"No":"64","me":"くくく、タイ人の女子校生～\nあぁ～　早くオマンコに入れてぇ～！\nさっさと失神してくれよぉ～！"},
{"No":"65","me":"おいおい、次は頼むぜ～！\nもっとビビらせねぇと、タイのオマンコを逃してしまうぞ！"},
{"No":"66","me":"くぅ～！　最後かよ～　異国から来たオマンコに射精する\nチャンスなのによぉ～！\n絶対、ヤる！　絶対犯すぜぇ～！"},
{"No":"67","me":"ゴクン！　オムツ大丈夫かなぁ～？\nきっとズッシリと　重くなってんじゃないのかなぁ～？\nぐへへへへ！"},
{"No":"68","me":""},
{"No":"69","me":""},
{"No":"70","me":""},
{"No":"71","me":"ゴクン…\nなに？　ココ、なにがオキルんですかぁ～？"},
{"No":"72","me":"フフ、やっぱり子供だましデスかぁ～？\nニホンだしぃ、こんなモノかなぁ…"},
{"No":"73","me":"まぁ　オモシロイかもデスねぇー…\n今度はナニ出ますかぁ～？"},
{"No":"74","me":"マ、マズいかもぉ…　I'm shaking...\nこれコワイねぇ…"},
{"No":"75","me":"ノォ～　なんだかアタマ来ちゃうよぉ～\nガッカリだよぉ～"},
{"No":"76","me":"コワイっ　コワくて　オモシロイねぇー！\nI'm so excited!"},
{"No":"77","me":"はぁはぁはぁ！\nコワイコワイっ　ガクガクしてるよぉ～！\nI'm scared!"},
{"No":"78","me":"ううっ…　オムツ　悪いネ…\nI need to change my underwear!"},
{"No":"79","me":"股が、股が気持ち悪ネー！　歩きヅライよ…"},
{"No":"80","me":"コワイね、これコワイよ…　オムツもコワイ…\nヤダよぉー…\nNo more!"},
{"No":"81","me":"オ、オシッコ…\nNo, why? ...\nSuddenly I have to pee..."},
{"No":"82","me":"イタタっ…　お腹イタイね…\nOh no, I have to take a dump! ..."},
{"No":"83","me":"モリー　日本人バカにしやがって～…\nお前は、何が怖いんだぁ～！？"},
{"No":"84","me":"う～む…　楽勝とは行かねぇかぁ…\nさて、今度はどの道具を試すかなぁ～！"},
{"No":"85","me":"粘るじゃねぇか～…\n次の道具で卒倒させてやるぜぇ～！\n覚悟しな！…"},
{"No":"86","me":""},
{"No":"87","me":"えっと…　ココで何か出るの？…\nえぇ…　ドキドキしますネ…"},
{"No":"88","me":"もっとコワイと思ってたヨ…\nまだ、これからなんデスかぁ？…"},
{"No":"89","me":"これゾクゾクしまぁす！　なんだか楽しくなってキマした！\n次はナニでるのかなぁ！？"},
{"No":"90","me":"Нет!　Мне страшно!\nうう…　今度ナニ！？　ナニ出てくるー！？"},
{"No":"91","me":"えぇー…\nニホンの肝だめしって、こんな感じデスかぁ～？"},
{"No":"92","me":"コレ楽しいぃ！　今度ナニ！？　はやく　はやくぅ～！\nわくわく！"},
{"No":"93","me":"もうヤですー！　足震えてマスー！…\nはぁはぁはぁ…\nЯ не могу перестать трястись..."},
{"No":"94","me":"あぁ…　オムツ　ツラいね…　湿ってマァス…"},
{"No":"95","me":"あうぅっ…　面白いけどぉ…\nオムツが…　オムツが気持ちわるいデス…"},
{"No":"96","me":"うぐうぐぅっ…　コ、コワイし、コカン気持ち悪い…\nこ、コマリマスよ～…"},
{"No":"97","me":"А?　Моча!\nオ、オシッコしたいネ…"},
{"No":"98","me":"Ай! ...зачем?\nお、お腹がイタイね…　ウ、ウ、ウン、コ…"},
{"No":"99","me":"オルガちゃぁ～ん　アナタはナニが怖いのかなぁ～？\nぐふふ！　ぐふふぅ～！"},
{"No":"100","me":"オルガちゃぁ～ん　今度はナニを試そうかなぁ～？\nオジさん頑張って、失神させちゃうからねぇ～！"},
{"No":"101","me":"オ、オルガちゃん！　アナタはナニが怖いの！？…\nこれで失神してくれないと、オジさんのチンポが泣い\nちゃうよ！"},
{"No":"102","me":""},
{"No":"103","me":"な、なにかココに出ますか！？…　え！？\nなになに！？　うううぅ！"},
{"No":"104","me":"あ、あまり怖くない気がしマスねぇ…\nまだまだ　これからデスかぁ？"},
{"No":"105","me":"い、いいデスねぇ、次なに出るかがワクワクです！"},
{"No":"106","me":"マズいね、コレ怖いよ！　ヤバいデスよ！…\nヤバいよ　ヤバいよー！"},
{"No":"107","me":"こ、怖くないデスねぇ…　これ小さい子レベル！？\nワタシ、バカにされてマスかぁ！？"},
{"No":"108","me":"オモシロイね！　今度はナニ出て来るかぁ！？\nたのしみデス！"},
{"No":"109","me":"怖いデスよ！　ダメだよ、怖いデスからっ！…\nはぁはぁはぁ！…"},
{"No":"110","me":"うぅー…\nオムツ気持ちワルいよ…　ぐちゅぐちゅ…"},
{"No":"111","me":"楽しいけど…　オムツがダメです…\nはぁ…"},
{"No":"112","me":"怖いっ　オムツダメ！　いやデスー！…\nうっ　うっ…"},
{"No":"113","me":"アウッ！…　プアット チー…\nあれ！？　オ、オシッコ！…　あれ…？\nし、したいっ…"},
{"No":"114","me":"アウッ！…　プアット キー…\nあれ！？　ウンコ！…　あれ…？\nし、したいっ…"},
{"No":"115","me":"さてさて～　タイの娘っ子は何で失神しちゃうんでしょう\nかねぇ～！？"},
{"No":"116","me":"さぁて、今度は何を　お見舞いしちゃおっかなぁ～！？\nさっと倒れてくれよぉ～！"},
{"No":"117","me":"くぅ～！　これでぶっ倒れてくれよぉ～！\nそうじゃないと俺のチンポが　ひどく悲しむからよぉ～！"},
{"No":"118","me":""},
{"No":"119","me":""},
{"No":"120","me":""},
{"No":"121","me":""},
{"No":"122","me":""},
{"No":"123","me":""},
{"No":"124","me":""},
{"No":"125","me":""},
{"No":"126","me":""},
{"No":"127","me":""},
{"No":"128","me":""},
{"No":"129","me":""},
{"No":"130","me":""},
{"No":"131","me":""},
{"No":"132","me":""},
{"No":"133","me":""},
{"No":"134","me":""},
{"No":"135","me":""},
{"No":"136","me":""},
{"No":"137","me":""},
{"No":"138","me":""},
{"No":"139","me":""},
{"No":"140","me":""},
{"No":"141","me":""},
{"No":"142","me":""},
{"No":"143","me":""},
{"No":"144","me":""},
{"No":"145","me":""},
{"No":"146","me":""},
{"No":"147","me":""},
{"No":"148","me":""},
{"No":"149","me":""},
{"No":"150","me":""},
{"No":"151","me":""},
{"No":"152","me":""},
{"No":"153","me":""},
{"No":"154","me":""},
{"No":"155","me":""},
{"No":"156","me":""},
{"No":"157","me":""},
{"No":"158","me":""},
{"No":"159","me":""},
{"No":"160","me":""},
{"No":"161","me":""},
{"No":"162","me":""},
{"No":"163","me":""},
{"No":"164","me":""},
{"No":"165","me":""},
{"No":"166","me":""},
{"No":"167","me":""},
{"No":"168","me":""},
{"No":"169","me":""},
{"No":"170","me":""},
{"No":"171","me":""},
{"No":"172","me":""},
{"No":"173","me":""},
{"No":"174","me":""},
{"No":"175","me":""},
{"No":"176","me":""},
{"No":"177","me":""},
{"No":"178","me":""},
{"No":"179","me":""},
{"No":"180","me":""},
{"No":"181","me":""},
{"No":"182","me":""},
{"No":"183","me":""},
{"No":"184","me":""},
{"No":"185","me":""},
{"No":"186","me":""},
{"No":"187","me":""},
{"No":"188","me":""},
{"No":"189","me":""},
{"No":"190","me":""},
{"No":"191","me":""},
{"No":"192","me":""},
{"No":"193","me":""},
{"No":"194","me":""},
{"No":"195","me":""},
{"No":"196","me":""},
{"No":"197","me":""},
{"No":"198","me":""},
{"No":"199","me":""},
{"No":"200","me":""},
{"No":"201","me":""},
{"No":"202","me":""},
{"No":"203","me":""},
{"No":"204","me":""},
{"No":"205","me":""},
{"No":"206","me":""},
{"No":"207","me":""},
{"No":"208","me":""},
{"No":"209","me":""},
{"No":"210","me":""},
{"No":"211","me":""},
{"No":"212","me":""},
{"No":"213","me":""},
{"No":"214","me":""},
{"No":"215","me":""},
{"No":"216","me":""},
{"No":"217","me":""},
{"No":"218","me":""},
{"No":"219","me":""},
{"No":"220","me":""},
{"No":"221","me":""},
{"No":"222","me":""},
{"No":"223","me":""},
{"No":"224","me":""},
{"No":"225","me":""},
{"No":"226","me":""},
{"No":"227","me":""},
{"No":"228","me":""},
{"No":"229","me":""},
{"No":"230","me":""},
{"No":"231","me":""},
{"No":"232","me":""},
{"No":"233","me":""},
{"No":"234","me":""},
{"No":"235","me":""},
{"No":"236","me":""},
{"No":"237","me":""},
{"No":"238","me":""},
{"No":"239","me":""},
{"No":"240","me":""},
{"No":"241","me":""},
{"No":"242","me":""},
{"No":"243","me":""},
{"No":"244","me":""},
{"No":"245","me":""},
{"No":"246","me":""},
{"No":"247","me":""},
{"No":"248","me":""},
{"No":"249","me":""},
{"No":"250","me":""},
{"No":"251","me":""},
{"No":"252","me":""},
{"No":"253","me":""},
{"No":"254","me":""},
{"No":"255","me":""},
{"No":"256","me":""},
{"No":"257","me":""},
{"No":"258","me":""},
{"No":"259","me":""},
{"No":"260","me":""},
{"No":"261","me":""},
{"No":"262","me":""},
{"No":"263","me":""},
{"No":"264","me":""},
{"No":"265","me":""},
{"No":"266","me":""},
{"No":"267","me":""},
{"No":"268","me":""},
{"No":"269","me":""},
{"No":"270","me":""},
{"No":"271","me":""},
{"No":"272","me":""},
{"No":"273","me":""},
{"No":"274","me":""},
{"No":"275","me":""},
{"No":"276","me":""},
{"No":"277","me":""},
{"No":"278","me":""},
{"No":"279","me":""},
{"No":"280","me":""},
{"No":"281","me":""},
{"No":"282","me":""},
{"No":"283","me":""},
{"No":"284","me":""},
{"No":"285","me":""},
{"No":"286","me":""},
{"No":"287","me":""},
{"No":"288","me":""},
{"No":"289","me":""},
{"No":"290","me":""},
{"No":"291","me":""},
{"No":"292","me":""},
{"No":"293","me":""},
{"No":"294","me":""},
{"No":"295","me":""},
{"No":"296","me":""},
{"No":"297","me":""},
{"No":"298","me":""},
{"No":"299","me":""},
{"No":"300","me":""},
{"No":"301","me":""},
{"No":"302","me":""},
{"No":"303","me":""},
{"No":"304","me":""},
{"No":"305","me":""},
{"No":"306","me":""},
{"No":"307","me":""},
{"No":"308","me":""},
{"No":"309","me":""},
{"No":"310","me":""},
{"No":"311","me":""},
{"No":"312","me":""},
{"No":"313","me":""},
{"No":"314","me":""},
{"No":"315","me":""},
{"No":"316","me":""},
{"No":"317","me":""},
{"No":"318","me":""},
{"No":"319","me":""},
{"No":"320","me":""},
{"No":"321","me":""},
{"No":"322","me":""},
{"No":"323","me":""},
{"No":"324","me":""},
{"No":"325","me":""},
{"No":"326","me":""},
{"No":"327","me":""},
{"No":"328","me":""},
{"No":"329","me":""},
{"No":"330","me":""},
{"No":"331","me":""},
{"No":"332","me":""},
{"No":"333","me":""},
{"No":"334","me":""},
{"No":"335","me":""},
{"No":"336","me":""},
{"No":"337","me":""},
{"No":"338","me":""},
{"No":"339","me":""},
{"No":"340","me":""},
{"No":"341","me":""},
{"No":"342","me":""},
{"No":"343","me":""},
{"No":"344","me":""},
{"No":"345","me":""},
{"No":"346","me":""},
{"No":"347","me":""},
{"No":"348","me":""},
{"No":"349","me":""},
{"No":"350","me":""},
{"No":"351","me":""},
{"No":"352","me":""},
{"No":"353","me":""},
{"No":"354","me":""},
{"No":"355","me":""},
{"No":"356","me":""},
{"No":"357","me":""},
{"No":"358","me":""},
{"No":"359","me":""},
{"No":"360","me":""},
{"No":"361","me":""},
{"No":"362","me":""},
{"No":"363","me":""},
{"No":"364","me":""},
{"No":"365","me":""},
{"No":"366","me":""},
{"No":"367","me":""},
{"No":"368","me":""},
{"No":"369","me":""},
{"No":"370","me":""},
{"No":"371","me":""},
{"No":"372","me":""},
{"No":"373","me":""},
{"No":"374","me":""},
{"No":"375","me":""},
{"No":"376","me":""},
{"No":"377","me":""},
{"No":"378","me":""},
{"No":"379","me":""},
{"No":"380","me":""},
{"No":"381","me":""},
{"No":"382","me":""},
{"No":"383","me":""},
{"No":"384","me":""},
{"No":"385","me":""},
{"No":"386","me":""},
{"No":"387","me":""},
{"No":"388","me":""},
{"No":"389","me":""},
{"No":"390","me":""},
{"No":"391","me":""},
{"No":"392","me":""},
{"No":"393","me":""},
{"No":"394","me":""},
{"No":"395","me":""},
{"No":"396","me":""},
{"No":"397","me":""},
{"No":"398","me":""},
{"No":"399","me":""},
{"No":"400","me":""},
{"No":"401","me":""},
{"No":"402","me":""},
{"No":"403","me":""},
{"No":"404","me":""},
{"No":"405","me":""},
{"No":"406","me":""},
{"No":"407","me":""},
{"No":"408","me":""},
{"No":"409","me":""},
{"No":"410","me":""},
{"No":"411","me":""},
{"No":"412","me":""},
{"No":"413","me":""},
{"No":"414","me":""},
{"No":"415","me":""},
{"No":"416","me":""},
{"No":"417","me":""},
{"No":"418","me":""},
{"No":"419","me":""},
{"No":"420","me":""},
{"No":"421","me":""},
{"No":"422","me":""},
{"No":"423","me":""},
{"No":"424","me":""},
{"No":"425","me":""},
{"No":"426","me":""},
{"No":"427","me":""},
{"No":"428","me":""},
{"No":"429","me":""},
{"No":"430","me":""},
{"No":"431","me":""},
{"No":"432","me":""},
{"No":"433","me":""},
{"No":"434","me":""},
{"No":"435","me":""},
{"No":"436","me":""},
{"No":"437","me":""},
{"No":"438","me":""},
{"No":"439","me":""},
{"No":"440","me":""},
{"No":"441","me":""},
{"No":"442","me":""},
{"No":"443","me":""},
{"No":"444","me":""},
{"No":"445","me":""},
{"No":"446","me":""},
{"No":"447","me":""},
{"No":"448","me":""},
{"No":"449","me":""},
{"No":"450","me":""},
{"No":"451","me":""},
{"No":"452","me":""},
{"No":"453","me":""},
{"No":"454","me":""},
{"No":"455","me":""},
{"No":"456","me":""},
{"No":"457","me":""},
{"No":"458","me":""},
{"No":"459","me":""},
{"No":"460","me":""},
{"No":"461","me":""},
{"No":"462","me":""},
{"No":"463","me":""},
{"No":"464","me":""},
{"No":"465","me":""},
{"No":"466","me":""},
{"No":"467","me":""},
{"No":"468","me":""},
{"No":"469","me":""},
{"No":"470","me":""},
{"No":"471","me":""},
{"No":"472","me":""},
{"No":"473","me":""},
{"No":"474","me":""},
{"No":"475","me":""},
{"No":"476","me":""},
{"No":"477","me":""},
{"No":"478","me":""},
{"No":"479","me":""},
{"No":"480","me":""},
{"No":"481","me":""},
{"No":"482","me":""},
{"No":"483","me":""},
{"No":"484","me":""},
{"No":"485","me":""},
{"No":"486","me":""},
{"No":"487","me":""},
{"No":"488","me":""},
{"No":"489","me":""},
{"No":"490","me":""},
{"No":"491","me":""},
{"No":"492","me":""},
{"No":"493","me":""},
{"No":"494","me":""},
{"No":"495","me":""},
{"No":"496","me":""},
{"No":"497","me":""},
{"No":"498","me":""},
{"No":"499","me":""},
{"No":"500","me":""},
{"No":"501","me":""},
{"No":"502","me":""},
{"No":"503","me":""},
{"No":"504","me":""},
{"No":"505","me":""},
{"No":"506","me":""},
{"No":"507","me":""},
{"No":"508","me":""},
{"No":"509","me":""},
{"No":"510","me":""},
{"No":"511","me":""},
{"No":"512","me":""},
{"No":"513","me":""},
{"No":"514","me":""},
{"No":"515","me":""},
{"No":"516","me":""},
{"No":"517","me":""},
{"No":"518","me":""},
{"No":"519","me":""},
{"No":"520","me":""},
{"No":"521","me":""},
{"No":"522","me":""},
{"No":"523","me":""},
{"No":"524","me":""},
{"No":"525","me":""},
{"No":"526","me":""},
{"No":"527","me":""},
{"No":"528","me":""},
{"No":"529","me":""},
{"No":"530","me":""},
{"No":"531","me":""},
{"No":"532","me":""},
{"No":"533","me":""},
{"No":"534","me":""},
{"No":"535","me":""},
{"No":"536","me":""},
{"No":"537","me":""},
{"No":"538","me":""},
{"No":"539","me":""},
{"No":"540","me":""},
{"No":"541","me":""},
{"No":"542","me":""},
{"No":"543","me":""},
{"No":"544","me":""},
{"No":"545","me":""},
{"No":"546","me":""},
{"No":"547","me":""},
{"No":"548","me":""},
{"No":"549","me":""},
{"No":"550","me":""}
]









